Workbook

Sheet Summary
A1: wa | B1: Digital Transformation - Business Process Reengineering (BPR)
B2: This sheet is the master tracker for Silverleaf's school-wide Systems Automation Programme. It documents every process improvement initiative across all seven departments — capturing current challenges, proposed solutions, implementation type, resources, and priorities. It is the central reference point for the project team, department heads, and leadership as we execute this project.
B4: Purpose of this project
B5: To systematically automate and digitize core processes across every department so Silverleaf can operate efficiently, consistently, and at scale as we expand Nationally across East Africa.
B7: Department | C7: Focus Area | D7: Total Processes | E7: Primary Type | F7: Key Areas | I7: System Links
A8: 1 | B8: Operations | C8: Transport, Kitchen, Facilities | D8: 11 | E8: Automated | F8: Transport, Kitchen, Facilities, Sanitation, Security
A9: 2 | B9: Finance | C9: Income, Expenses & Inventory | D9: 12 | E9: Automated | F9: Billing & Collections, Expense Management, Inventory Tracking
A10: 3 | B10: Marketing & Admissions | C10: Enrollment, CRM & Communications | D10: 13 | E10: Automated / SOP | F10: Enrollment, Campus Tours, CRM, Digital Marketing, Parent Retention | I10: https://bit.ly/marketingSIS
A11: 4 | B11: HR | C11: People, Payroll & Development | D11: 16 | E11: Automated / AI-powered | F11: Recruitment, Onboarding, Performance, Payroll, Compliance
A12: 5 | B12: Data, Tech & MEL | C12: Systems, Data & Reporting | D12: 6 | E12: Automated | F12: Ed-admin, MEL, IT Systems, Asset Management
A13: 6 | B13: Student Experience | C13: Welfare, Boarding & Engagement | D13: 9 | E13: Automated / Tech enabled | F13: Safeguarding, Boarding, Trips, Daycare, Parent Engagement | I13: https://bit.ly/marketingSIS
A14: 7 | B14: Academic | C14: Teaching, Learning & Quality | D14: 11 | E14: Tech enabled | F14: Teaching & Learning, Assessment, Data, Professional Development
A15: 8 | B15: Expansion | C15: Data Collection and Reporting | D15: 9 | E15: Tech enabled | F15: Data collection,Centralization of Records and Reporting
B17: Column | C17: Label | D17: What it means
B18: A | C18: SN No. | D18: A unique reference number for each process (e.g. 1.1, 1.2) so the team can refer to specific items quickly in meetings and reports
B19: B | C19: Process / Department | D19: The name of the specific process or area being improved within the department
B20: C | C20: Current Challenge | D20: A clear description of what is not working today and why it is a problem for the organization
B21: D | C21: Proposed Improvement | D21: What will be done to fix it — the specific solution, system, or workflow that will be implemented
B22: E | C22: Intended Solution | D22: How the improvement will be delivered: Automated, Tech enabled, Standardized (SOP), or a combination
B23: F | C23: Link / Resources | D23: The current system or tool being used (e.g. Ed-admin, Runshule, Google Forms) — this shows what platform the solution will be built on or integrated with. For the ones which are not linked, it's the system the team wish to have that can perform similar task
B24: G | C24: Priority | D24: All items on the priority list are planned to be completed within 3 months
B26: User Experiences - HCD | F26: Developed Systems Links
B27: S/N | C27: Stakeholder Type
B28: 1 | C28: Parent Experience | D28: Different parent personas
B29: 2 | C29: Student Experience
B30: 3 | C30: HR | D30: Different Staff personas - UX map
B31: 4 | C31: Suppliers
B32: 5
C33: KP & NZ raise
B34: Total raise | C34: 2.2M total raise
B35: Timeline | C35: 2026 Sept - Dec 2028 (28 months)
B36: Total schools | C36: 12 (7,500 students total)
B37: Breakeven year | C37: 2029
B38: EBITA Steady state | C38: 0.2
B39: Net Margin (steady state) | C39: 0.15
B40: Committed | C40: 1.3M already commited | D40: Apollo Investments ($800k), DEG ($200k), Ali Jaffer ($300k)
B41: Status | C41: Term sheet final sign off next week
B42: Close date | C42: 4M pre money valuation
B43: Type | C43: Straight equity
B44: Funder shortlist - 3 highest liklihood | C44: HNWIs (Netflix Founder), Pansophic, Acumen, | D44: 900k remaining
B45: Timing | C45: Signing term sheets by end july. Disbusrsments Sept

Sheet 6. Student Experience
A1: S/N | B1: Process / Area | C1: Current Challenge | D1: Proposed Improvement | E1: Intended Solution | F1: Current System | G1: Priority | H1: Notes
A2: 6.1 | B2: Student Wellness & Clinic Records | C2: Medical records are kept manually, making it difficult to track frequent visits, monitor health trends, or share relevant information with parents promptly. | D2: Deploy a digital student health management system with visit logs, medical history records, parent alerts, and a leadership dashboard for visibility. | E2: Automated / Tech enabled | F2: Student health system | G2: 1
A3: 6.2 | B3: Student Incident & Child Protection Reporting | C3: Incidents are reported via paper forms or WhatsApp, causing delays, incomplete records, and difficulty following up on cases consistently. | D3: Introduce a centralized digital incident reporting system with case tracking, automated alerts, and secure documentation to ensure every report is recorded and followed up. | E3: Automated / Tech enabled | F3: Incident reporting system | G3: 2
A4: 6.3 | B4: Co-Curricular Attendance & Participation Tracking | C4: Attendance at co-curricular activities is tracked manually and inconsistently, making it difficult to measure participation levels or assess impact. | D4: Deploy a QR or digital attendance system with participation dashboards and automated reports so leaders and teachers have clear visibility of engagement. | E4: Ed-admin | F4: Ed-admin | G4: 3
A5: 6.4 | B5: Co-Curricular Scheduling & Communication | C5: Frequent schedule changes are not communicated effectively to parents, teachers, and students, creating confusion and missed activities. | D5: Create a centralized activities calendar synced with the parent app, staff portal, and student dashboard so all stakeholders receive updates automatically. | E5: Ed-admin | F5: Ed-admin | G5: 4
A6: 6.5 | B6: Boarding Student Welfare & Routines Monitoring | C6: Welfare logs are maintained manually and reporting is inconsistent, limiting leadership visibility into the daily wellbeing of boarding students. | D6: Implement a digital residential management system with daily welfare logs, structured checklists, and a leadership dashboard for real-time oversight. | E6: Ed-admin | F6: Ed-admin | G6: 5
A7: 6.6 | B7: Residential Walkthrough & Cleanliness Audits | C7: Walkthroughs are not consistently logged and there is no structured way to track patterns, assign action points, or monitor follow-through. | D7: Introduce a mobile checklist tool with photo evidence capture, issue tagging, and auto-generated reports so walkthroughs are structured and findings are actioned. | E7: Automated / Standardized | F7: Mobile audit tool | G7: 6
A8: 6.7 | B8: Parent Workshops & Event Management | C8: Sign-ins at events are manual and there is limited data available on participation levels or attendee satisfaction. | D8: Introduce online event registration, QR check-in, automated reminders, and a post-event feedback system to improve attendance tracking and event quality. | E8: Automated / Tech enabled | F8: Event management system | G8: 7
A9: 6.8 | B9: Student Recognition & Awards Tracking | C9: Recognition records are scattered across different systems and individuals, making it difficult to ensure fairness, consistency, or visibility of achievements. | D9: Deploy a digital recognition tracker with nomination forms, criteria-based scoring, and individual student achievement profiles to make recognition structured and transparent. | E9: SOP (Simple google form created to track all students receiving awards just for the record) | G9: 8
A10: 6.9 | B10: Learning and Behaviour Management | C10: Behavior incidents are documented manually, communication with parents is delayed, and follow-up is inconsistent across staff and campuses. | D10: Introduce a behavior tracking system with automated parent notifications, structured intervention logs, and trend reports to support consistent and timely responses. | E10: Ed-admin | F10: Ed-admin | G10: 9

Sheet Priority List
A1: Key Process | B1: Dept | C1: Process / Area | D1: Process Lead | E1: Current Challenge | F1: Proposed Improvement | G1: Intended Solution | H1: Current System | I1: Priority | J1: Notes
A2: 1 | B2: Academic | C2: Digital lesson plans | D2: Ruth/Julius /Aloyce/Anthonia | E2: Building a Silverleaf-specific version of Rumi (Taleemabad's open-source AI education tool). Taleemabad has made the code for Rumi freely available, which gives us a strong starting point instead of building an AI teaching tool from scratch. The challenge is that the version we currently have access to is set up generically as "Rumi for Tanzania" — it isn't tailored to Silverleaf's curriculum, branding, campuses, or way of working. To make it genuinely useful for our teachers and students, we need to clone the open-source code and stand up a separate, dedicated instance built specifically for Silverleaf Academy. This means setting up our own version, adapting it to our content and context, and maintaining it ourselves, rather than relying on a shared national setup that doesn't reflect how Silverleaf actually operates. | F2: Clone and deploy a dedicated Silverleaf Academy instance of Rumi, customised with our own content, branding, and context — hosted and maintained independently of the shared national setup. | G2: A standalone Rumi for Education instance fully tailored to Silverleaf Academy teachers and students, with content ownership and the ability to update and adapt it as needed.
A3: 2 | B3: Academic | C3: Rumi for Education (AI Coaching) | D3: Julius
A4: 3 | B4: Finance | C4: Requisition Process | D4: Dan, Lillian (Nelly) | E4: Digitising and streamlining the requisition and vendor payment process. Right now, the way requests are made across our campuses, departments, and central team is largely manual and inconsistent. Requests are shared through email, WhatsApp, Google Sheets, and word of mouth, which makes them hard to track and easy to lose. Because requests come in through so many different channels, the finance team often has to re-enter or re-organise the same information themselves, creating double work. There's also no single, clear path showing who raised a request, which department or campus it came from, who needs to approve it, what stage it's at, and when the vendor is actually paid. This slows down approvals and payments, creates confusion over what's been ordered, spent, or still owed, and makes it difficult to keep proper records. The challenge is to move this onto one digital process — with a standard request form, clear approval steps, and a way to track every requisition through to vendor payment — so requests from any campus, department, or the central team are faster, more transparent, properly documented, and don't create extra work for finance. | F4: Introduce automated payment scheduling and batch payment preparation so that vendor payments are processed on time and fully traceable. It include internet, ELectricity and suppliers payments across campuses. | G4: Automated reminders for the finance team to be able to work on these payments
A5: 4 | B5: HR | C5: Staff Onboarding & Orientation | D5: Esther, Nelly [Mourine] | E5: Standardising staff onboarding and orientation. We bring on new hires fairly regularly across our campuses, departments, and central team, but right now there's no single, consistent way to welcome and set them up. Onboarding often happens informally and differs from one campus or department to another, so the experience a new staff member gets depends on who happens to be handling it. Important steps — like setting up accounts and tools, sharing key policies and documents, explaining how Silverleaf works, and introducing them to their team — can be missed, delayed, or repeated. This leaves new hires unclear on what's expected of them, slows down how quickly they become productive, and creates extra last-minute work each time someone joins. The challenge is to build one clear, standard onboarding and orientation process — with a checklist of steps, the right documents and access ready in advance, and a consistent welcome experience — so every new hire, on any campus or in any department, is set up properly and the same way each time. | F5: Build a standardised onboarding checklist and resource hub within Silverleaf's systems — covering tool access, key documents, policies, and a consistent welcome flow that applies to any campus or department. | G5: Every new hire, regardless of campus or department, goes through the same clear orientation process with the right documents, system access, and welcome experience — reducing delays and inconsistency.
A6: 5 | B6: Operations/Finance | C6: Inventory & Asset Management | D6: Baraka, Dan (Nelly) [Nehemia] | E6: Inventory and asset management remains a challenge due to the lack of a centralized and reliable tracking system for school resources. Assets such as laptops, tablets, projectors, furniture, and classroom materials are often spread across campuses or departments without clear ownership or accurate location records, making them difficult to track and manage. Stock levels for consumable supplies are not always visible in real time, leading to shortages or unnecessary purchases. Manual record-keeping also makes inventory checks time-consuming and prone to error, while limited tracking of maintenance and repairs reduces accountability and can result in lost, damaged, or underutilized resources. | F6: Introduce a centralised digital asset register with real-time stock visibility, clear ownership records per campus and department, and automated alerts for low consumables and scheduled maintenance checks. | G6: A single source of truth for all Silverleaf assets — enabling staff to see what exists, where it is, who is responsible, and when maintenance or restocking is needed, reducing loss and unnecessary spending.
A7: 6 | B7: Fundraising Pipeline | C7: Fundraising program | D7: Krupa
A8: 6 | B8: Operations | C8: Transport – Fuel Control | D8: Baraka | E8: Fuel costs represent a significant and growing operational expense across Silverleaf's campuses, yet there is currently no centralised system in place to track consumption, monitor usage patterns, or calculate cost per kilometre. Vehicles are used across multiple campuses and departments without consistent logging of trips, distances, or fuel purchases, making it difficult to attribute costs accurately or identify where inefficiencies exist. Without visibility into how fuel is being consumed, it is impossible to know whether vehicles are being used appropriately, whether certain routes or drivers are disproportionately costly, or whether the current fleet size is justified. This lack of oversight also means that budget forecasting for fuel is largely based on estimates rather than reliable data, leading to either overspending or underfunding. The absence of accountability mechanisms further compounds the problem — there is no way to flag unusual consumption, detect misuse, or hold departments responsible for their usage. As a result, Silverleaf continues to absorb avoidable costs with no clear path to reducing them. | F8: Implement a centralised fuel tracking system that logs consumption, distance travelled, and cost per kilometre for each vehicle across all campuses and departments. The system should capture data per driver or vehicle, generate regular usage reports, and flag anomalies such as sudden spikes in consumption or cost. Integrating this with budget management tools would allow finance teams to monitor fuel expenditure in real time and allocate costs accurately to the relevant campus or department | G8: A single, transparent fuel management dashboard that gives Silverleaf real-time visibility into vehicle usage and costs — enabling data-driven decisions on fleet efficiency, reducing unnecessary expenditure, and ensuring accountability across all campuses.
A9: 7 | B9: Data, Tech & MEL - TAKE OFF | C9: MEL database | D9: Katya, Paul | E9: MEL processes remain a challenge because we currently lack a centralized database to consolidate monitoring, evaluation, and learning data in one place. Reports are often stored across different spreadsheets, tools, or departments, making it difficult to access complete information quickly, track progress consistently, or compare data over time. This fragmentation creates inefficiencies in reporting, limits visibility into program performance, increases manual work during data collection and analysis, and makes it harder for teams to generate timely insights for decision-making. | F9: Build or adopt a centralised MEL database that consolidates monitoring, evaluation, and learning data in one place — with standardised data entry, shared access for relevant staff, and built-in reporting tools. | G9: A unified MEL platform that allows teams to track progress, generate reports, and compare data across programs and time periods with minimal manual effort — supporting faster, more evidence-based decisions.
A11: 8 | B11: Recruitment | C11: Recruitment process as a whole | D11: Esther, Nelly [Mourine]

Sheet Operations Department
A1: S/N | B1: Process / Area | C1: Current Challenge | D1: Proposed Improvement | E1: Intended Solution | F1: Current System | G1: Priority | H1: Notes
A2: 1.1 | B2: KPI Reporting (All Departments) | C2: Reports are generated manually, causing delays and providing no real-time visibility of operational performance. | D2: Auto-generate KPI dashboards across Transport, Kitchen, Facilities, and other departments. Automatically compare Target vs Actual (e.g., on-time %, budget vs actual) in real time. | E2: Automated | F2: Finance Master Sheet | G2: 1
A3: 1.2 | B3: Budget Tracking | C3: The department lacks real-time visibility into budget utilization, making it difficult to track remaining funds against the approved budgeted amount. | D3: Deploy a Budget vs Actual dashboard so leaders can track expenditure in real time and identify overspend early. | E3: Ed-admin | F3: Finance budget sheet | G3: 2 | H3: General ledger and budgeting mmodule currently. tested by Finance team, will ensure all departments send their budget requests through Ed admin.
A4: 1.3 | B4: Transport – Attendance System | C4: Student attendance on transport is tracked manually, leading to errors and delayed reporting. | D4: Implement a QR code scanning system linked to a live dashboard with automated attendance reports. | E4: Automated (Andama System) to be piloted | F4: QR tracking system is being piloted | G4: 3 | H4: There is a system currently being piloted by Ops team, which can be looked at. Currently Development System(web system and Android application) is developed that has capabiilitities to generate QR code,sync infomations with the Android app and scanning qrcode to collect attendance
A5: 1.4 | B5: Transport Attendance system – (QR) → Finance Integration | C5: There is no link between transport attendance and student fee status, and parents are not notified promptly. | D5: Link QR code scans to the student finance database. Automatically check fee status on scan and trigger SMS/WhatsApp alerts to parents when a balance is pending or overdue. | E5: Automated | F5: Manual process | G5: 4 | H5: Integrate the Above system with finance records which will add more functionalities to the system e.g Payment recharge
A6: 1.5 | B6: Data Integration | C6: Operational systems are not connected, requiring manual data transfer and creating inconsistencies. | D6: Build a Central Operations Master System that integrates all departmental data into a single, accessible platform. | E6: Automated - Central ops system | G6: 5
A7: 1.6 | B7: Transport – Route Optimization | C7: Transport routes are inefficient, resulting in long travel times and unnecessary fuel costs. | D7: Implement GPS-based route optimisation to reduce travel time and fuel expenditure across all routes. | E7: Tech enabled - GPS route planning tool | G7: 6
A8: 1.7 | B8: Transport – Occupancy Tracking | C8: Buses are either under or over-utilised due to a lack of real-time occupancy visibility. | D8: Introduce an automated occupancy dashboard so transport managers can monitor utilisation and allocate vehicles efficiently. | E8: Tech enabled- Occupancy dashboard | G8: 8
A9: 1.8 | B9: Facilities – Asset Management | C9: Assets across campuses are not clearly tracked, making it difficult to maintain accountability or plan replacements. Also maintanance requests need to be tracked clearly | D9: Create an asset register with QR tagging and condition tracking so all assets are logged, located, and monitored. | E9: Tech enabled- Asset register system (Ed Admin) | G9: 9
A10: 1.9 | B10: Security – Entry/Exit Control | C10: Visitor and contractor access is logged manually, creating a security risk and poor audit trail. | D10: Introduce a digital visitor log with ID or QR verification so all entry and exit is recorded accurately and securely. | E10: Tech enabled-Digital visitor log | G10: 10
A11: 1.11 | B11: Staff-to-Operations Team Reporting System | C11: Staff report Ops. related issues to operations department via calls and emails. | D11: Introduce an automated reporting tool to capture issues raised by staff and forward them to the Operations Team to resolve | E11: Automated / Tech-enabled | G11: 11
A12: 1.12 | B12: Students & Parents Data access | C12: The Ops team has no single source of truth when it comes to parents and students information | D12: Have a single source of truth, (Database) to ensure they have access to the correct details at all times. | E12: Ed-admin | F12: Enrollment dashboards | G12: 12

Sheet 2. Finance
A1: S/N | B1: Process / Area | C1: Current Challenge | D1: Proposed Improvement | E1: Intended Solution | F1: Current System | G1: Priority | H1: Notes
A2: 2.1 | B2: Revenue Reporting | C2: School fee collection data is consolidated manually, making it slow to produce accurate and up-to-date revenue reports. | D2: Build automated dashboards showing real-time collection status, outstanding balances, and payment trends across current and previous years. | E2: Ed-admin | F2: Runshule | G2: 1 | H2: Ed admin through the Fee adminsistration module can resolve this challenge, the team will be onboarded into the module and test it with two campuses (AM and Ilboru)
A3: 2.2 | B3: Expense Request | C3: Staff submit expense requests through multiple informal channels, creating fragmentation and making it difficult to track or process requests efficiently. | D3: Develop a simple, accessible app that allows any staff member to submit an expense request directly, ensuring all requests are captured in one place. | E3: Automated system that allows staff to submit their requests directly | G3: 2 | H3: Requisitions & Purchasing module from Ed adin. The Finance team has been trained o how to do it. Further support available
A4: 2.3 | B4: Expense Internal Approvals | C4: Approval routing is handled manually, causing delays and creating the risk of duplicate or unauthorized requests passing through undetected. | D4: Implement an automated approval workflow with a defined hierarchy, real-time alerts at each stage, and automatic detection of duplicate submissions. | E4: Automated expense system to allow full circle from Expense submission, approvals, payment and receipt submitted | G4: 3 | H4: Requisitions & Purchasing module from Ed adin. The Finance team has been trained o how to do it. Further support available
A5: 2.4 | B5: Inventory Tracking | C5: Stock movements are recorded manually and updates are irregular, resulting in inaccurate inventory balances for items such as uniforms and supplies. | D5: Deploy an automated stock movement tracking system with a simple app interface for logging distribution, usage, or sales, ensuring inventory balances are always current. | E5: Automated inventory management system | G5: 4
A6: 2.5 | B6: Inventory Controls & Spot Audits | C6: Stock variances between physical counts and system records are difficult to identify quickly, weakening inventory controls. | D6: Introduce automated variance reporting and real-time alerts when physical stock levels differ from system records, supported by structured spot audit SOPs. | E6: Automated inventory management system | G6: 5
A7: 2.6 | B7: Receivables Monitoring & Follow-up | C7: Overdue balances are tracked manually, leading to delayed follow-up and inconsistent communication with parents. | D7: Deploy automated overdue reminders and escalation alerts for unpaid balances so that follow-up is triggered on time and tracked centrally. | E7: Automated Bulk SMS/Emails and reminders sent to parents automaticaly Ed admin Parents Portal has these capabilities as well. | F7: Runshule | G7: 6 | H7: Runshule has a bulk SMS and Fee reminders feature currently used.
A8: 2.7 | B8: Vendor Payments | C8: Payment scheduling and tracking is done manually, increasing the risk of missed or late payments to vendors. | D8: Introduce automated payment scheduling and batch payment preparation so that vendor payments are processed on time and fully traceable. It include internet, ELectricity and suppliers payments across campuses. | E8: Automated reminders for the finance team to be able to work on these payments | G8: 7
A9: 2.8 | B9: Receipting & Petty Cash | C9: Paper receipts are used for petty cash and uploads are frequently delayed, reducing the accuracy of financial records. | D9: Implement a digital receipting system linked to the accounting platform, allowing staff to upload receipts immediately and reducing errors in petty cash tracking. | E9: Tech enabled | G9: 8 | H9: Explore Ed admin and other systems
A10: 2.9 | B10: Collections & Receipt Allocation | C10: Bank payments are matched to student accounts manually, causing errors and delays in confirming receipt of payment. | D10: Automate the matching of bank payments to student accounts and generate TRA receipts automatically. Send payment confirmations to parents via WhatsApp and SMS immediately upon allocation. | E10: Ensure we have a receipting systems where parents can receive TRA receipts immediately after making payment | F10: Runshule | G10: 9 | H10: Ed admin through the Fee adminsistration module can resolve this challenge, the team will be onboarded into the module and test it with two campuses (AM and Ilboru)
A11: 2.11 | B11: Bank Reconciliation | C11: Bank reconciliation is performed manually and is time-consuming, delaying the availability of accurate financial data. | D11: Automate bank statement imports, transaction matching, and daily reconciliation reporting so that accounts are reconciled continuously and accurately. | E11: Automated bank reconciliation on a daily basis to ensure consistency in data and reporting. | F11: QuickBooks | G11: 10
A12: 2.12 | B12: Budget vs Actual Monitoring | C12: Monthly budget vs actual reports are prepared manually, making them slow to produce and difficult to keep current. | D12: Automate the posting of transactions against budget lines and generate real-time dashboards showing budget vs actual performance across all cost centres. | E12: Automated QuickBook reports that allows dashboards to be generated for ease of visibility and monitoring | F12: QuickBooks | G12: 11
A13: 2.13 | B13: Student Billing & Fee Invoicing | C13: Fee invoices are created or adjusted manually, creating room for error and inconsistency across student accounts. | D13: Automate fee generation based on enrollment data, transport, boarding, and other approved charges so that invoices are produced accurately and without manual intervention. | E13: Invoicing automation via Runshule, despite students having different fees amounts to pay on an annual basis | F13: Runshule Step-to-step student invoicing | G13: 12 | H13: Ed admin through the Fee adminsistration module can resolve this challenge, the team will be onboarded into the module and test it with two campuses (AM and Ilboru)

Sheet 3. Marketing
A1: S/N | B1: Process / Area | C1: Current Challenge | D1: Proposed Improvement | E1: Intended Solution | F1: Current System | G1: Priority | H1: Notes
A2: 3.1 | B2: Enrollment Process | C2: The admissions process is largely manual and dependent on individual staff, leaving room for errors, missed follow-ups, and an inconsistent experience for prospective parents. | D2: Deploy an intelligent chatbot on the website and WhatsApp to instantly answer common parent questions about fees, admissions requirements, and deadlines. Automate lead capture and connect it directly to the CRM so no inquiry is missed. Send automated status updates and document verification alerts to parents throughout the application process. Set up automated follow-up sequences via email and WhatsApp to keep prospective families engaged. Standardize admissions handling with clear SOPs for all staff to follow. | E2: Ed-admin - admissions form | F2: Google sheets (Enrollment sheets) | G2: 1 | H2: Ed-admi admissions module has the ability to capture leads information from the. first time they inquire about the school. The form is ready to be shared with parents for ease of making an application. Here is the Ed admin admissions form
A3: 3.2 | B3: Campus Tour & Appointment Booking | C3: Campus tours depend on walk-ins and are not structured, making it difficult to manage capacity, prepare the team, or follow up with visiting families systematically. | D3: Launch a self-service booking system accessible via the website, WhatsApp, or email so parents can schedule tours at their convenience. Send automated booking confirmations to parents and notify the internal team immediately. Set up calendar reminders at 24 hours and on the day of the tour. Automatically share a pre-tour information pack covering the school profile and what to expect. Trigger a follow-up message and feedback request after each visit. | E3: Automated | F3: Phone calls to school admin office and random parent walkins | G3: 2
A4: 3.3 | B4: Partnerships & Institutional Outreach | C4: Partnerships with corporates, feeder schools, and community organizations are informal and inconsistent, limiting their contribution to enrollment growth. | D4: Build a structured partnership pipeline in the CRM covering corporates, feeder schools, and key organizations. Track all outreach activity and relationship history centrally so nothing falls through the gaps. Automate initial outreach emails and follow-up reminders for partnership conversations. Define clear partnership offerings such as fee discounts, priority admissions, and co-branded events. Send regular partner updates and performance reports to maintain strong relationships. | E4: Automated / SOP | G4: 3
A5: 3.4 | B5: Admissions Funnel Management | C5: There are no clearly defined stages for the admissions journey, making it difficult to track where prospective families are, identify drop-off points, or intervene at the right time. | D5: Define clear funnel stages: Inquiry → Tour → Application → Enrollment. Automate the movement of leads between stages based on actions taken. Set up follow-up triggers at each stage so no family goes without contact. Track conversion rates at every stage to identify where families are dropping off. Create re-engagement campaigns for leads who have gone quiet. | E5: Automated / SOP | G5: 4
A6: 3.5 | B6: Digital Marketing | C6: The school's online presence is inconsistent and not generating enough leads from digital channels to support enrollment targets. | D6: Optimize the school website with clear enrollment calls to action on every key page. Run targeted paid advertising campaigns on Google and social media to reach parents actively searching for schools. Develop a social media content calendar and schedule posts in advance for consistency. Build dedicated landing pages for specific campaigns to improve conversion rates. Connect all lead capture forms directly to the CRM so leads are tracked from first contact. | E6: Automated | F6: Website, Social & Ads | G6: 5
A7: 3.6 | B7: Marketing Events | C7: Events are under-optimized and not consistently used as an opportunity to capture leads and convert prospective families. | D7: Automate pre-event promotion through email, WhatsApp, and paid ads. Use digital registration forms linked to the CRM to capture attendee details before the event. Set up on-site lead capture for walk-in attendees. Automate post-event follow-up messages and next-step invitations. Track event performance from attendance through to enrollment to measure return on investment. | E7: Automated / SOP | G7: 6
A8: 3.7 | B8: Mass Communications | C8: Parent and prospect communications are one-directional, not personalized, and often delayed — reducing their effectiveness in driving action. | D8: Set up automated email and WhatsApp communication flows for key stages of the parent journey. Segment messaging by audience: new leads, active applicants, enrolled parents, and lapsed prospects. Send broadcast updates and reminders for key dates and announcements. Trigger communications automatically based on specific events or actions. Personalize messaging where possible using data from the CRM. | E8: Automated | G8: 7
A9: 3.9 | B9: Community Engagement | C9: Community outreach efforts are unplanned and inconsistent, limiting the school's visibility and its ability to convert community presence into enrollment. | D9: Plan a structured community outreach calendar aligned to the school year and key enrollment windows. Ensure the school has a visible presence at local events and within key institutions and organizations. Track all community engagement activity in the CRM to maintain relationships and measure impact. Capture stories and content from community activities to use in marketing and social media. Run follow-up engagement campaigns after community events to nurture new leads. | E9: SOP | G9: 9
A10: 3.11 | B10: Sales & Commissions | C10: The admissions team does not have a structured sales process, and individual performance is not consistently tracked or rewarded based on results. | D10: Define a clear, step-by-step sales process with scripts and guidance for each stage of the funnel. Link commission structures directly to enrollment conversions to drive motivation and accountability. Track individual performance metrics per admissions staff member in the CRM. Set up automated reminders for follow-ups so no lead is left uncontacted. Integrate the sales process fully with CRM and funnel tracking for end-to-end visibility. | E10: Automated / SOP | G10: 10
A11: 3.12 | B11: Data Analytics & Performance Tracking | C11: Marketing performance is not tracked in real time, meaning decisions are made reactively rather than based on current data. | D11: Build real-time dashboards tracking leads, conversions, and enrollments at every funnel stage. Monitor key KPIs including cost per lead, conversion rates, and performance by source. Track all campaign performance across ads, events, and referral programs. Generate automated monthly performance reports for leadership review. Analyse funnel drop-off points to identify where improvements will have the most impact. | E11: Automated | F11: Leads dashboard | G11: 11
A12: 3.13 | B12: CRM System | C12: Leads and parent interactions are not tracked centrally, causing missed follow-ups, duplicated effort, and no visibility of the full parent journey. | D12: Set up a centralized CRM that captures every lead from all sources: website, WhatsApp, events, and walk-ins. Auto-assign leads to team members with deadlines and reminders to ensure prompt follow-up. Track the full parent journey from first inquiry through to enrollment and long-term retention. Store all communication history in one place so any team member can see the full picture. Automate follow-up triggers so no lead goes cold without an intervention. | G12: 12
A13: 3.14 | B13: Parent Experience & Retention | C13: Once a family enrolls, structured engagement largely stops — reducing satisfaction, limiting referrals, and increasing the risk of families leaving. | D13: Build an automated welcome and onboarding journey for all newly enrolled families. Send regular newsletters and school updates to keep parents informed and connected. Collect feedback consistently and respond in a timely and visible way. Launch a referral program with automated prompts and tracking to encourage word-of-mouth growth. Personalize engagement around key moments such as student milestones and achievements. | E13: Automated / SOP | G13: 13

Sheet 4. HR
A1: S/N | B1: Process / Area | C1: Current Challenge | D1: Proposed Improvement | E1: Intended Solution | F1: Current System | G1: Priority | H1: Notes
A2: 4.2 | B2: Recruitment & Hiring | C2: The hiring process is largely manual, creating room for errors and inconsistency. Key steps depend on individual follow-through rather than structured automation. | D2: Automate the end-to-end hiring workflow so that emails, task assignments, and candidate communications are triggered automatically. Human involvement is reserved for reviewing and decision-making only. | E2: Automated/Tech enabled(Simplified Comms system between HR and Candidates) | F2: View Link | G2: 2
A3: 4.3 | B3: Staff Files & Records Management | C3: Employee information is collected manually and stored inconsistently, making it difficult to maintain accurate and up-to-date staff records. | D3: Use pre defined system to collect staff data digitally and automatically store responses in a centralized, structured record system that is accessible and auditable. | E3: Ed admi | F3: Link | G3: 3
A4: 4.4 | B4: Leave Management | C4: Tracking leave across multiple campuses is difficult and time-consuming, with no real-time visibility of balances or approvals. | D4: Deploy an automated leave tracker with structured approval workflows and real-time visibility of leave balances and status across all campuses and locations. | E4: Ed admin leave managemet module | F4: Ed-Admin | G4: 4 | H4: Stup on the back end already done and team is trained
A5: 4.5 | B5: Employer Branding & HR Communication | C5: Recruitment marketing is done manually and has limited reach, making it harder to attract quality candidates consistently. | D5: Implement AI-powered recruitment marketing tools to optimize job advertisements, automate social media posting, and track candidate engagement across channels. | E5: Automated / AI | F5: — | G5: 5
A6: 4.6 | B6: Performance Management,Probation Period Management | C6: Appraisal forms are completed manually, feedback is often delayed, and tracking progress against goals is difficult without a central system.Probation start and end dates, performance reviews, and notice periods are tracked manually, increasing the risk of missed milestones or delayed action. | D6: Deploy an online performance management system with automated appraisal cycles, goal-tracking dashboards, and AI-generated performance summaries to support timely and consistent reviews.Implement an automated probation tracking system that sends reminders for key milestones, collects performance feedback digitally, and notifies HR and line managers when action is required. This will also include managers to fill forms and comments on the staffs they manage to have a real data to make decisions | E6: Automated / AI | F6: — | G6: 6
A7: 4.7 | B7: Health, Safety & Workplace Environment | C7: Incident reporting is done manually and safety compliance is difficult to monitor consistently across campuses. | D7: Introduce a digital incident reporting system with automated escalation alerts and a safety compliance tracking dashboard so that all incidents are logged and followed up promptly. | E7: Automated | F7: — | G7: 7
A8: 4.8 | B8: Training & Development Talent Management & Succession Planning | C8: Training planning is done manually and there is no structured way to identify or address skill gaps across the staff population.There is no structured process for identifying high-potential staff or planning for future leadership needs across the organization. | D8: Deploy a Learning Management System (LMS) that recommends courses based on role and performance data, sends automated training reminders, and issues digital certificates upon completion.Deploy an AI talent mapping system that analyses performance data, training history, and leadership assessments to identify high-potential staff and support succession planning decisions. | E8: Automated / AI | F8: — | G8: 9
A9: 4.9 | B9: Compensation & Benefits | C9: Benefits information is tracked manually and staff frequently contact HR with routine questions about payslips, allowances, and entitlements. | D9: Launch a digital self-service benefits portal where staff can view their payslips, benefits, and allowances at any time, supported by an AI chatbot to handle common queries without HR involvement. | E9: Training | F9: Paytan | G9: 10
A10: 4.11 | B10: Employee Engagement & Culture,Employee Relations | C10: Staff feedback is collected irregularly and overall engagement levels are difficult to measure or act on in a structured way. | D10: Introduce automated pulse surveys with AI-powered engagement analysis dashboards and sentiment tracking so that leadership has a continuous and reliable view of staff wellbeing and morale. | E10: Automated / AI | F10: — | G10: 13
A11: 4.12 | B11: HR Compliance & Legal Issues | C11: Policy updates and contract compliance tracking are handled manually, creating risk of missed contract renewals or incomplete documentation. | D11: Implement an automated contract lifecycle management system with digital signatures, automated compliance alerts for expiring contracts, and notifications for missing or incomplete documentation. | E11: Automated and Notification system | F11: — | G11: 14
A12: 4.13 | B12: HR Planning & Strategy | C12: Workforce planning is done using spreadsheets with no data-driven approach to forecasting staffing needs or anticipating turnover. | D12: Deploy an AI workforce planning tool that predicts future staffing needs based on enrollment trends and historical turnover patterns, enabling proactive and evidence-based planning. | E12: AI-powered(data and planning System) | F12: — | G12: 15
A13: 4.14 | B13: HR Data, Analytics & Reporting | C13: HR reports are prepared manually and are time-consuming to produce, delaying access to key people data for leadership decisions. | D13: Build a real-time HR analytics dashboard that integrates recruitment, onboarding, leave, performance, and turnover data, with AI-generated insights to support strategic decisions. | E13: Automated / AI(Dashboard) | F13: — | G13: 16
A14: 4.15 | B14: Staff Attendance | C14: Done manuallly on using books where staff write their names and signature while clocking and clock out | D14: Make it on a digital system | E14: Ed-Admin staff attendance module | F14: Manual books | G14: 17 | H14: Setup and training completed, HR team has to keep using the system

Sheet 5. Data, Tech & MEL 
A1: S/N | B1: Process / Area | C1: Current Challenge | D1: Proposed Improvement | E1: Intended Solution | F1: Current System | G1: Priority | H1: Notes
A2: 5.1 | B2: Academic & School Systems | C2: Data is split between Google Sheets and Ed-admin, creating duplication and gaps in visibility. Key academic data such as walkthrough records cannot flow seamlessly between systems. | D2: Establish Ed-admin as the single source of truth for all academic data. Remove parallel use of Google Sheets and replace with automated data entry flows. | E2: Tech enabled/SOP | F2: Ed-admin | G2: 1
A3: 5.2 | B3: Digital Systems Management | C3: Account creation requests arrive through multiple informal channels. There is no standardized process, which leads to delays, missed steps, and no clear record of system access or license ownership. | D3: Route all account creation requests through the HR system. Once a new staff member is added, an automated notification triggers the provisioning process. | E3: Automated(system intergration) | G3: 2 | H3: The HR system has ability to send email to notify if the user needs to have an email when the candidate is qualified to join silverleaf for the first time.
A4: 5.3 | B4: Monitoring, Evaluation & Learning | C4: MEL data is stored across multiple tools and formats with no consistent structure. This makes it difficult to generate reliable insights or support evidence-based decisions. | D4: Bring all MEL materials into a single organized folder structure with clearly labeled shortcuts for quick access. | E4: Tech enabled/SOP | G4: 3 | H4: 2026 MEL FOLDER
A5: 5.4 | B5: Asset Management (Tech Devics management) | C5: Devices and equipment are tracked manually using spreadsheets. Records become outdated quickly, ownership is unclear, and accountability across campuses is difficult to enforce. | D5: Deploy a centralized asset management system with automated workflows covering device registration, assignment, transfers, and status tracking. | E5: Tech enabled(Asset tracking system) | G5: 4
A6: 5.5 | B6: Training Management | C6: Staff training is not tracked centrally and lacks a standard format. Completion rates are unknown, follow-up is inconsistent, and knowledge retention varies significantly across campuses. | D6: Implement a Learning Management System (LMS) to standardize, deliver, and track all staff training from a single platform. | E6: online based, Professional development and learning system) | G6: 5
A7: 5.6 | B7: IT Systems & Support | C7: IT issues are reported informally via email or in person. There is no central log, making it hard to track progress, assign ownership, or identify recurring problems. | D7: Introduce a centralized ticketing system where every issue is logged, assigned, and tracked through a defined resolution workflow. keeping track of solutions that solved problem occured, users can also add userful tips related to tech like links to courses, videos and pictures | E7: Tech enabled(Ticketing system) | G7: 6

Sheet 7. Academic Department
A1: S/N | B1: Process / Area | C1: Current Challenge | D1: Proposed Improvement | E1: Intended Solution | F1: Current System | G1: Priority | H1: Notes
A2: 7.1 | B2: Academic Data & Insights | C2: Data underutilised for decision-making; no teacher-level insights; learning gaps not identified or addressed in a timely manner. | D2: Build automated dashboards for teachers and leadership; introduce digital intervention tracking to address learning gaps promptly. | E2: Ed admin- Tech enabled | F2: Academic Master Sheet - SLA Standard | G2: 1 | H2: WIll require Ed admin API ($750 per Annum)
A3: 7.2 | B3: Student Support & Intervention | C3: Students identified late for support; remedial provision is inconsistent; no early identification system or automated risk flagging. | D3: Implement automated alert system with risk flags; deploy structured digital program assignment and a small-group intervention scheduler. | E3: Ed admin- Tech enabled | F3: Manual Process | G3: 2 | H3: To be covered by academic data and insights
A4: 7.3 | B4: Staff Professional Development | C4: New teachers lack structured onboarding; PD not tracked or aligned to subject needs; scheduling conflicts common; no measurable link between PD and outcomes. | D4: Deploy digital induction modules, PD attendance dashboards, subject-specific PD trackers, automated scheduling reminders, and outcome-linked dashboards. | E4: Telemabad | F4: SLA 2025 PD and Coaching Plan | G4: 3 | H4: Find a way to link outcomes to be linked with Ed admin if we use the Talemabad kind of online training module
A5: 7.5 | B5: Parent & Community Engagement | C5: Parents not informed on time; unaware of homework expectations; low attendance at events; lack of overall engagement and awareness. | D5: Deploy automated SMS/WhatsApp/email alerts, digital homework sharing, digital event invites and reminders, and recorded/live digital parent workshops. | E5: Automated / Tech enabled | F5: WhatsApp, Phone calls, SMS, ED admin parent portal | G5: 5 | H5: Do a survey on the ease of use for EdAmin by parents, then if the score is above 70% implement the email comms system. If not decide whether to send tutorials or keep existing comms systems. Also explore using calendar & events on EdAdmin.
A6: 7.6 | B6: Teaching & Learning | C6: Inconsistent lesson quality and instructional models; ineffective routines; weak differentiation for varied learners; inconsistent checking for understanding; low classroom engagement. | D6: Deploy standardized lesson templates, observation tracking, digital instructional model guides, automated formative assessment tools, and engagement monitoring analytics. | E6: Tech enabled | F6: Lesson templates, engagement tools | G6: 6 | H6: Observation & Walkthrough dashboards to be developed
A7: 7.7 | B7: Technology Integration | C7: Low tech adoption in lessons; teachers underutilise devices; limited use of digital assessment tools across classrooms. | D7: Integrate EdTech platforms (Kahoot, ClassDojo, Quizizz); provide training with digital monitoring dashboards; deploy online assessment platforms with automated marking. | E7: SOP to guide Ed tech tools usage | G7: 7 | H7: Might be good to understand the cadence for implementation as this is more of a instruction and learning support design (under lesson plans) than Data and Analytics.
A8: 7.8 | B8: Academic Attainment | C8: Manual tracking of attainment against targets; performance varies across subjects; no class or campus-wide performance dashboards. | D8: Deploy automated digital dashboards tracking attainment by subject, class, and campus in real time. | E8: Data Dashboard from Ed admin reports | F8: EdTech platforms | G8: 9 | H8: This is will be covered under 7.1
A9: 7.9 | B9: Academic Operations & Systems | C9: Manual scheduling is time-consuming; class assignments are inefficient; lesson plans not monitored; quality reviews are inconsistent. | D9: Introduce automated timetable generator, system-generated class allocation, and a digital lesson plan submission and review platform. | E9: ASC Timetable software | F9: Timetable tools, submission platform | G9: 10 | H9: $149 one time payment to have our own scheduler
A10: 7.91 | B10: Learning Resource & Library | C10: Unequal resource access; manual borrowing system; resources outdated; students not motivated to read; limited access to online materials. | D10: Implement digital inventory and allocation system, automated library management, digital reading rewards tracker, and a centralized digital learning repository. | E10: SOP to guide books borrowing (hard copies) and consider a server like Rachel for digital use | F10: No system | G10: 11 | H10: This will be implemented on EdAdmin, for Library Circulation and Inventory management. An online repository will require a feasibility study i.e how many devices can we avail, and internet connectivity.

Sheet 8.Expansion
A1: S/N | B1: Process / Area | C1: Current Challenge | D1: Proposed Improvement | E1: Intended Solution | F1: Link / Resources | G1: Priority
A2: 8.1 | B2: Site Sourcing & Consultant Pipeline | C2: Potential schools are identified informally through consultants and networks with no central tracking. Consultant reporting is inconsistent, making it hard to compare opportunities. | D2: Create a structured digital pipeline for all potential acquisition, lease, or purchase opportunities. Standardise consultant reporting using a digital form capturing: school name, owner contact, location, student numbers, asking price/lease terms, facilities, and photos. All entries feed directly into the central database. | E2: Automated / SOP | G2: 1
A3: 8.2 | B3: Expansion Opportunity Database | C3: Site information is not stored centrally, making follow-up, comparison, and decision-making difficult. | D3: Build and maintain a centralised database for all potential schools and sites, capturing: status, documents, photos, GPS coordinates, consultant notes, scoring history, and decision outcomes. This is the single source of truth for all expansion activity. | E3: Automated / SOP | G3: 2
A4: 8.3 | B4: Pre-Screening & Site Scoring | C4: Key information is often incomplete before field visits. There is no clear scoring method to decide which sites are actually worth visiting, wasting the Expansion Officer's time. | D4: Combine a pre-screening checklist (to collect key details before any visit) with an automated scoring tool that ranks sites based on: location, student population, facility condition, growth potential, price, accessibility, and strategic fit. Only sites that meet the minimum score threshold proceed to a full field visit. | E4: Automated / SOP | G4: 3
A5: 8.4 | B5: Field Due Diligence & Site Assessment | C5: Field visits capture inconsistent data across locations. Site GPS is not recorded for strategic mapping. Facility conditions and market/student potential are not assessed using a common framework, making cross-site comparison unreliable. | D5: Create one comprehensive mobile due diligence form (used by the Expansion Officer on-site) covering four integrated areas: • Location & GPS: Capture GPS coordinates; all sites plotted on a live map showing status and priority score. • Facility & Infrastructure: Classrooms, toilets, water, electricity, kitchen, playground, safety, repairs needed, and upgrade cost estimate. • Student & Market Potential: Current enrolment, nearby population, competing schools, fee levels, parent demand, and growth projection. • Visit Summary: Photos, risks, notes, and overall site recommendation. | E5: Automated | F5: Currently in use | G5: 4
A6: 8.5 | B6: Financial & Commercial Assessment | C6: Pricing, lease terms, acquisition costs, and upgrade costs are not analysed consistently across different sites, making financial comparison difficult. | D6: Create a standard financial assessment template to compare: acquisition or lease cost, renovation/upgrade cost, expected enrolment, projected revenue, operating cost estimate, and payback period. Output feeds into the site review summary and leadership approval pack. | E6: Automated | G6: 5
A7: 8.6 | B7: Decision Review & Leadership Approval | C7: Decisions rely on scattered notes rather than a structured recommendation. Approvals are delayed because information is incomplete or not packaged clearly for leadership. | D7: Combine into a single workflow: (1) Auto-generate a standard site review summary with score, risks, opportunity, photos, financial estimate, and recommendation. (2) Submit shortlisted sites to leadership through a structured approval workflow with all required documents and recommendation notes attached. Leadership can approve, reject, or request more information within the system. | E7: Automated / SOP | G7: 6
A8: 8.7 | B8: Negotiation Tracking | C8: Negotiations with school owners and landlords are not tracked systematically, leading to missed follow-ups and unclear terms. | D8: Track all active negotiations in the expansion database: negotiation status, agreed terms, pending issues, documents requested, counterparty contacts, and next steps. Automated reminders for follow-up actions. | E8: Automated | G8: 7
A9: 8.8 | B9: Acquisition / Lease Handover | C9: Once a site is approved, the handover to Finance, Legal, Operations, and Academics is not structured, creating risk of tasks falling through the gaps. | D9: Create a post-approval handover checklist that automatically assigns responsibilities across Finance (payment/contracts), Legal (due diligence/agreements), Operations (setup), and Academics (campus readiness). Each department receives a task notification with deadline. | E9: Automated / SOP | G9: 8
A10: 8.9 | B10: Expansion Dashboard & Reporting | C10: Leadership does not have real-time visibility on the expansion pipeline — how many sites are being tracked, at what stage, and what the projected outcome is. | D10: Build a live dashboard showing: sites sourced, pre-screened, visited, shortlisted, rejected, under negotiation, approved, and projected school capacity. Accessible to KP and leadership at any time without requiring manual reports from the Expansion Officer. | E10: Automated / SOP | G10: 9

Sheet Ed Admin Modules
A1: ED-ADMIN — FEATURES BY FUNCTION AREA
A3: # | B3: FUNCTION AREA | C3: FEATURES | D3: % OF TOTAL | E3: In Use | F3: MODULE DESCRIPTION | G3: IMPLEMENTATION STATUS | H3: NOTES
A4: 1 | B4: Admissions | C4: 23 | D4: 0.15231788 | F4: Manages student applications, enrollment, and admission process. | G4: Completed & Used
A5: 2 | B5: Communications | C5: 10 | D5: 0.066225166 | F5: Facilitates emails, SMS, and notifications between school, staff, and parents. | G5: Completed & Used
A6: 3 | B6: Portals & Mobile Apps | C6: 10 | D6: 0.066225166 | E6: 5 | F6: Used for remote access | G6: Completed
A7: 4 | B7: Fee Administration | C7: 10 | D7: 0.066225166 | E7: 0 | G7: In Progress | H7: Nova are using Ed-admin for all accounts eceivables by the receivables team by preparing billing, upload MPesa/Bank statements to the SIS to update all student fee informatin and parents can receive reports through the Multi portal App.
A8: 5 | B8: Calendar & Events | C8: 9 | D8: 0.059602649 | F8: Schedules school-wide events, activities, and important dates. | G8: Not Started
A9: 6 | B9: Student Records | C9: 8 | D9: 0.052980132 | F9: Centralized database for student personal, academic, and historical records. | G9: Completed & Used
A10: 7 | B10: Academic Management | C10: 6 | D10: 0.039735099 | F10: Handles subjects, grading structures, and academic workflows and setup. | G10: Completed & Used
A11: 8 | B11: General Ledger & Budgeting | C11: 6 | D11: 0.039735099 | G11: Not Started
A12: 9 | B12: Assessment Premium | C12: 5 | D12: 0.033112583 | F12: Advanced tool for tracking, analyzing, and reporting student assessments. | G12: Completed & Used
A13: 10 | B13: Dashboard | C13: 4 | D13: 0.026490066 | G13: Completed
A14: 11 | B14: Parent Records | C14: 4 | D14: 0.026490066 | E14: 3 | F14: Stores parent/guardian contact details and relationships to students. | G14: Completed & Used
A15: 12 | B15: Pastoral Care | C15: 4 | D15: 0.026490066 | G15: Not Started
A16: 13 | B16: Attendance | C16: 4 | D16: 0.026490066 | F16: Tracks daily student attendance, tardiness, and absences. | G16: Completed & Used
A17: 14 | B17: Curriculum Management & LMS | C17: 4 | D17: 0.026490066 | G17: Not Started
A18: 15 | B18: Learning & Behaviour (LBM) | C18: 4 | D18: 0.026490066 | F18: Tracks student behaviour, discipline, and academic interventions. | G18: Not Started
A19: 16 | B19: Server & Infrastructure | C19: 4 | D19: 0.026490066 | G19: Not Started
A20: 17 | B20: Staff Leave Management | C20: 3 | D20: 0.01986755 | F20: Manages all staff leave requests, approvals and keep records of all staff leave management resuests | G20: Completed & Used
A21: 18 | B21: Staff Attendance | C21: 3 | D21: 0.01986755 | F21: Tracks daily staff attendance, late arrivals, and absences. | G21: Completed
A22: 19 | B22: Activity Management | C22: 3 | D22: 0.01986755 | F22: Organizes extracurricular activities, clubs, and student participation. | G22: Not Started
A23: 20 | B23: Learning Support | C23: 3 | D23: 0.01986755 | G23: Not Started
A24: 21 | B24: Library | C24: 3 | D24: 0.01986755 | G24: Not Started
A25: 22 | B25: Inventory | C25: 3 | D25: 0.01986755 | G25: Not Started
A26: 23 | B26: Helpdesk & Asset Register | C26: 3 | D26: 0.01986755 | G26: Not Started
A27: 24 | B27: Enquiry | C27: 2 | D27: 0.013245033 | G27: Not Started
A28: 25 | B28: Bills Payable | C28: 2 | D28: 0.013245033 | G28: Not Started
A29: 26 | B29: Requisitions & Purchasing | C29: 2 | D29: 0.013245033 | G29: Not Started
A30: 27 | B30: Transport Management | C30: 2 | D30: 0.013245033 | G30: Not Started
A31: 28 | B31: Alumni & Donor Management | C31: 2 | D31: 0.013245033 | G31: Not Started
A32: 29 | B32: Alumni Portal & App | C32: 2 | D32: 0.013245033 | G32: Not Started
A33: 30 | B33: Accounting — General | C33: 1 | D33: 0.0066225166 | G33: Not Started
A34: 31 | B34: Contacts | C34: 1 | D34: 0.0066225166 | G34: Not Started
A35: 32 | B35: Supplier Payments | C35: 1 | D35: 0.0066225166 | G35: Not Started
B36: TOTAL | C36: =sum(C4:C35) -> 151 | D36: =sum(D4:D35) -> 1

Sheet Ed admin Full Feature List
B1: ED-ADMIN — COMPLETE FEATURE LIST
B5: Total Features: 151 | Function Areas: 30 | Source: Ed-Admin Complete Feature List
B7: # | C7: FUNCTION AREA | D7: FEATURE NAME | E7: DESCRIPTION | F7: Implementation Status
B8: ▶ ADMISSIONS
B9: 1 | C9: Admissions | D9: Online Application — Website Integration | E9: Enrolment application form integrated into the school website and Ed-Admin, capturing data and delivering it directly to the Admissions Module. | F9: In Progress
B10: 2 | C10: Admissions | D10: Online Application — Automatic Email Alerts | E10: Automatic email alerts sent to the Admissions Registrar when new applications are submitted online. | F10: In Progress
B11: 3 | C11: Admissions | D11: Online Application — Status Update Notifications | E11: Automatic email alerts sent to parents and admissions staff for all status updates throughout the application process. | F11: In Progress
B12: 4 | C12: Admissions | D12: Online Application — Configurable Process | E12: Application process can be configured for terms agreement, contact details, debit order information, and more. | F12: Will not be Used
B13: 5 | C13: Admissions | D13: Online Application — Payment Gateway Integration | E13: Application process can be integrated with an online payment gateway to collect application fees. | F13: Will not be Used
B14: 6 | C14: Admissions | D14: Online Application — Custom Fields | E14: User can add unlimited extra questions requiring date, numeric, text or dropdown selection responses. | F14: Will not be Used
B15: 7 | C15: Admissions | D15: Online Application — Parent & Dual Signatures | E15: Parents can digitally sign agreements and conditions. Optional dual-guardian sign-off: application only completes once both guardians have signed. | F15: Will not be Used
B16: 8 | C16: Admissions | D16: Online Application — Document Uploads | E16: Parents can upload supporting documents including school reports, birth certificates, and IDs. Student photo upload also supported. | F16: Not Started
B17: 9 | C17: Admissions | D17: Online Application — Field Configuration | E17: Full control over which fields are optional, mandatory, or disabled. Public-facing labels can be renamed up to 100 characters. | F17: Completed
B18: 10 | C18: Admissions | D18: Online Application — Branding | E18: Institution colours can be applied for branding. A full copy of the completed application is emailed to the primary guardian. | F18: Not Started
B19: 11 | C19: Admissions | D19: Admission Tracking — Data Management | E19: Parents capture application data into the core system; staff can add additional information or make changes. | F19: In Progress
B20: 12 | C20: Admissions | D20: Admission Tracking — Online Payments | E20: Payment for registration can be set up to process new applications online. | F20: Not Started
... B31: 23 | C31: Admissions | D31: Admission Reports | E31: Reports listing applications by grade, year of entry, or waiting list position. Configurable analysis reports for current year, upcoming year, and up to ten years into the future. | F31: Not Started
B32: ▶ CALENDAR & EVENTS
B33: 24 | C33: Calendar & Events | D33: Multiple Calendar Views | E33: Create multiple calendars in daily, weekly, monthly and term views under different categories. | F33: Not Started
B34: 25 | C34: Calendar & Events | D34: Venue & Event Booking | E34: Personalised, combined calendars allowing booking by venue or events. | F34: Not Started
B35: 26 | C35: Calendar & Events | D35: Parent-Teacher Meeting Bookings | E35: Create Parent/Teacher meeting bookings allowing parents to select and book time slots through the Parent App. | F35: Not Started
B36: 27 | C36: Calendar & Events | D36: Full Integration | E36: Calendar and events fully integrated with the Parent Web Portal and Mobile App. Published events shared across all Ed-Admin portals and apps. | F36: Not Started
B37: 28 | C37: Calendar & Events | D37: Parent Outings & Permissions | E37: Parents can authorise outings through Parent Portals and Mobile Apps. Reminder emails sent to non-responders. Response analysis shows who has or has not given permission. | F37: Not Started
B38: 29 | C38: Calendar & Events | D38: Google Calendar Integration | E38: Existing Google Calendars can be linked to show on Staff, Parent, and Student Mobile Apps. | F38: Not Started
B39: 30 | C39: Calendar & Events | D39: Actual & Virtual Calendars | E39: Actual calendars target selective staff by area of work. Virtual calendars share events selectively with parents on the Parent Web Portal and App. | F39: Not Started
B40: 31 | C40: Calendar & Events | D40: Calendar Communication Features | E40: Email invitees with event updates; take attendance for meeting events; take minutes; email minutes; book venues and resources including costing. | F40: Not Started
B41: 32 | C41: Calendar & Events | D41: Reports | E41: Reports showing events by venue and all events in a list view. | F41: Not Started
B42: ▶ COMMUNICATIONS
B43: 33 | C43: Communications | D43: Bulk SMS & Email | E43: Send bulk SMS and email to all parents, sponsors, debtors, or staff by grade, class, program, area of work, etc. | F43: Not Started
B44: 34 | C44: Communications | D44: Bulk Email Attachments | E44: Attach newsletters, account statements and report cards to bulk emails at the press of a button, eliminating complex attachment routines. | F44: Not Started
B45: 35 | C45: Communications | D45: Merge Codes & Personalisation | E45: A range of merge codes enables personalisation of every email and SMS with student/parent names, classes, years, and other data fields. | F45: Not Started
B46: 36 | C46: Communications | D46: Bulk Mobile App Notifications | E46: Send bulk notifications to Staff, Parent, Student, and Alumni Apps. Target specific audiences by grade, class, subject, activity, and house. | F46: Not Started
B47: 37 | C47: Communications | D47: Bulk News | E47: Create rich-text news with pictures to display on Staff, Parent, Student, and Alumni Apps. Set expiry dates for automatic removal of news items. | F47: Not Started
B48: 38 | C48: Communications | D48: Documentation Sharing | E48: Share documents with a selective audience via Apps. Create specific folders for school policies and general information. | F48: Not Started
B49: 39 | C49: Communications | D49: Bulk Label Printing | E49: Print class labels customised by size and merged data for younger and older students. | F49: Not Started
B50: 40 | C50: Communications | D50: Automated Emails & Triggers | E50: Automatically send communications based on triggers including: status changes, absences, merits/demerits, overdue library books, overdue fees, and more. | F50: Not Started
B51: 41 | C51: Communications | D51: Delivery & Open Tracking | E51: Track delivery and open/read status of all communications. Recipient summary showing number of families, guardians, and mobile app users reached. | F51: Not Started
B52: 42 | C52: Communications | D52: Report Writer Integration | E52: Link to the Report Writer to select specific recipients based on multiple criteria. | F52: Not Started
B53: ▶ DASHBOARD
B54: 43 | C54: Dashboard | D54: Information Hub | E54: Dynamic information portal with instant notice board for forums, news, events, and push notifications to Mobile Apps. | F54: Completed
B55: 44 | C55: Dashboard | D55: Budget Dashboard | E55: Users can view their transactions, data, and charts against budget codes directly on the dashboard. | F55: In Progress
B56: 45 | C56: Dashboard | D56: Data Snapshots | E56: Graphical data snapshots showing basic statistics about the school and students. | F56: Completed
B57: 46 | C57: Dashboard | D57: Security & Customisation | E57: Security levels restrict staff to data relevant to their department. Users can customise their own dashboard view. Ability to post media (pictures, videos) and add hyperlinks to news. | F57: Completed
B58: ▶ ENQUIRY
B59: 47 | C59: Enquiry | D59: Online Enquiry Form | E59: Complement your website with online enquiry forms for potential parents and students. Track and respond to all enquiries with status updates. | F59: In Progress
B60: 48 | C60: Enquiry | D60: Automatic Emails & Communication Log | E60: Enquiries automatically emailed to single or multiple addresses. View all communications with a party including dates, times, and staff member details. Assign follow-up actions. | F60: In Progress
B61: ▶ PORTALS & MOBILE APPS
B62: 49 | C62: Portals & Mobile Apps | D62: Parent Portal — Comprehensive Access | E62: Parents monitor student progress remotely: attendance, report cards, calendar, timetable, merits/demerits, activities, library, finance statements, health records, and more. One login for all children. | F62: Completed
B63: 50 | C63: Portals & Mobile Apps | D63: Student Portal — Academic Access | E63: Students view attendance, calendar, timetable, report cards, assessment marks, and access the full Learning Management System from any device. | F63: Will not be Used | G63: No access to students
B64: 51 | C64: Portals & Mobile Apps | D64: Customisable Portal Features | E64: Institutions control which features are shown or hidden: News, Calendar, Assessment Feed, LBM, Activities, Report Cards, Attendance, Communication, Library, Re-enrolment, Parent-Teacher Meetings, Finance, Health Records, Documents, and more. | F64: Completed
B65: 52 | C65: Portals & Mobile Apps | D65: Parent-Teacher Communication | E65: Direct email and messaging between parents, students, teachers, and staff from within the portal. Integrated email and chat functionality. | F65: In Progress
B66: 53 | C66: Portals & Mobile Apps | D66: Online Information Updates | E66: Parents and students update personal information, medical history, and contact details online; changes can be held pending institutional approval. | F66: Completed | G66: Sessions with parents to onboard them on the system required
B67: 54 | C67: Portals & Mobile Apps | D67: Finance on Portal | E67: View statements and outstanding balances, obtain and pay invoices, view fee account balances, and print past and present invoices via the portal. | F67: Not Started
B68: 55 | C68: Portals & Mobile Apps | D68: Subject & Activity Selection | E68: Students choose and enrol in elective subjects and extra-curricular activities via the portal. Requests may be approved by institution staff. | F68: Will not be Used
B69: 56 | C69: Portals & Mobile Apps | D69: Panic Button | E69: Students can quickly alert parents/guardians and related staff in an emergency. | F69: Will not be Used | G69: No access to students
B70: 57 | C70: Portals & Mobile Apps | D70: Health Screening & NFC/QR Integration | E70: Health screening via Staff App with NFC cards, barcodes and QR code integration. | F70: Will not be Used
B71: 58 | C71: Portals & Mobile Apps | D71: Branding & Auto-Invite | E71: Rich branding features for websites and mobile apps. Auto-invite feature sends reminders to parents, staff, students, and alumni to download the mobile app. | F71: Will not be Used
B72: ▶ PARENT RECORDS
B73: 59 | C73: Parent Records | D73: Comprehensive Sponsor Database | E73: Easy view of both guardians and sponsors on one screen. Option for additional guardians (Guardian 3 and 4). Contact, address, and emergency details all in one place. | F73: Completed
B74: 60 | C74: Parent Records | D74: Communication & Audit Log | E74: Communication log of all correspondence. Full audit history logging every action including portal login history. Password security compliant with POPI Act. | F74: Completed
B75: 61 | C75: Parent Records | D75: Reports & Analysis | E75: Parent analysis reports to identify missing records (emails, phone numbers, addresses). Sibling reports to see all related students. | F75: Completed
B76: 62 | C76: Parent Records | D76: Direct Email & SMS | E76: Send email or SMS directly to a parent with a click of a button from within the Parent Records module. | F76: Completed
B77: ▶ STUDENT RECORDS
B78: 63 | C78: Student Records | D78: Centralised Student Database | E78: Full registration information including start date, previous institution, and transfer details. Linked to parent records to avoid duplication. Powerful search by name, grade, class, or status. | F78: Completed
B79: 64 | C79: Student Records | D79: Academic & Attendance View | E79: View academic progress, extracurricular activities, attendance records, timetables, and fee schedules directly from within the Student module. | F79: Completed
B80: 65 | C80: Student Records | D80: Health Records | E80: Full health and medical records including screening, immunisation, medication, allergies, and pop-up allergy warnings. Secure permission levels to restrict sensitive information. | F80: Will not be Used
B81: 66 | C81: Student Records | D81: Communication Log | E81: Communication log showing all correspondence from the institution to the student. Direct email and SMS from student records. | F81: Not Started
B82: 67 | C82: Student Records | D82: Behaviour & Learning Support | E82: Quick view of LBM (merit/demerit) records. View learning support records including therapy, assessments, and exam accommodations. | F82: Not Started
B83: 68 | C83: Student Records | D83: Full Audit History | E83: Complete audit trail logging every change with user, computer, and event details. Portal login history tracked. | F83: Not Started
B84: 69 | C84: Student Records | D84: Reporting & Analysis | E84: Dynamic report writer. Class lists with photos and custom columns. Enrolment analysis, student data analysis (missing data, siblings, parent links), statistical reports by gender, nationality, religion, and class. | F84: Completed
B85: 70 | C85: Student Records | D85: Transfer & Custom Fields | E85: Access transfer cards and custom designs. National number capture (Lurits/Cemis). Student house reports. Student leaving/starting report by date range. | F85: Completed
B86: ▶ PASTORAL CARE
B87: 71 | C87: Pastoral Care | D87: House & Tutor Management | E87: Take attendance by house or tutor group on desktop and mobile. Exeat/leave system for boarders. Weekday restrictions and Saturday DT attendance. Housemaster access to student profiles for report writing. | F87: Will not be Used
B88: 72 | C88: Pastoral Care | D88: Behaviour & Discipline (LBM) | E88: Issue demerits and merits via desktop or mobile. Integrated academic and pastoral discipline system feeding appropriate workflows. Parent email notifications for demerits, merits, rewards and consequences. | F88: Will not be Used
B89: 73 | C89: Pastoral Care | D89: Health & Wellbeing Management | E89: Sick bay attendance feeding workflows and class registers. Medical information linked to student profile. Sick bay stocktake and inventory. Daily medication scripts. Charge student accounts for medicine. | F89: Will not be Used
B90: 74 | C90: Pastoral Care | D90: Safeguarding | E90: Safeguarding concerns and risks flagged and sent to appropriate Safeguard lead, initiating necessary workflows. | F90: Will not be Used
B91: ▶ LEAVE MANAGEMENT
B92: 75 | C92: Leave Management | D92: Online Leave Application | E92: All staff apply for leave online selecting from a range of leave types and attaching supporting documents. Email notifications to applicant and approval staff. Automated approval notifications. | F92: Completed
B93: 76 | C93: Leave Management | D93: Leave Approval Process | E93: Approval uses the Reporting To hierarchy from the HR module. Configurable approval tiers (1, 2, or 3 levels). Leave administrator can override approvals. Applications rejected with notes kept on record. | F93: Completed
B94: 77 | C94: Leave Management | D94: Paperless Leave Solution | E94: All leave application, documents and approvals are fully online. Leave administrators can stay in the loop, retract approved leaves, or intercept the approval process. | F94: Completed
B95: ▶ STAFF ATTENDANCE
B96: 78 | C96: Staff Attendance | D96: Biometric & RFID Integration | E96: Staff attendance taken manually or via biometric devices. Check-in/check-out records automatically populate Ed-Admin. Integration with leave management and HR database. | F96: Will not be Used
B97: 79 | C97: Staff Attendance | D97: Work Schedules | E97: Group staff into work schedule groups covering full-time, part-time and weekend staff. Exclude non-working days, public holidays, and term breaks. SMS and email notifications for late arrivals or early departures. | F97: Completed
B98: 80 | C98: Staff Attendance | D98: Reports & Communications | E98: Staff attendance reports across the whole institution or by specific campus. All communications personalised using merge codes. Configurable email templates for the Leave Administrator. | F98: In Progress
B99: ▶ ACADEMIC MANAGEMENT
B100: 81 | C100: Academic Management | D100: Subject & Class Management | E100: Manage full subject range, assign rooms to teachers, allocate teachers to subjects, enrol students in classes. Create sets and divisions within subjects. Copy and re-integrate timetables term to term. | F100: Completed
B101: 82 | C101: Academic Management | D101: Timetable Features | E101: Flexible period allocations (single, double, triple). Auto-detect conflict resolution. Import timetables from Excel, ASC, or Timetabler. Subject colour allocations. Multi-level student allocations across grades. | F101: Completed
B102: 83 | C102: Academic Management | D102: Assessment & Gradebooks | E102: Create custom gradebooks with flexible weightings. Bulk generate average and promotion marks. Set Year Mark weightings. SASAMS gradebook import for CAP schools. | F102: Completed
B103: 84 | C103: Academic Management | D103: Grade Schedules & Assessment Criteria | E103: Create schedules per grade matching percentages to letters or numbers (A*, A, B, C or 7, 6, 5, 4). Create assessment criteria linked to option sets (letters, numbers, symbols). | F103: Completed
B104: 85 | C104: Academic Management | D104: Report Cards | E104: Control subjects, comments, page sequence, images, and dates on report cards. Use comment banks. Bulk print by grade or class. Publish report cards to Mobile Apps with access control. | F104: Completed
B105: 86 | C105: Academic Management | D105: Academic Reports | E105: Range of standard and customisable analysis reports. Mark analysis, registers, class lists, reviews, and transcript generation. Export to PDF or print. Auto-populate term reports once assessments entered. | F105: In Progress
B106: ▶ ACTIVITY MANAGEMENT
B107: 87 | C107: Activity Management | D107: Cultural & Sports Groups | E107: Add/remove students and teachers from clubs, societies, music, and sports. Record co-curricular and sport involvement on student profiles. Take attendance via web and mobile app. | F107: Not Started
B108: 88 | C108: Activity Management | D108: Activity Categories & Classifications | E108: Create unlimited activity groups and sub-categories (music, extra-curricular, sports). Classify activities by age or grade (e.g. U12, U14, open). Minimum and maximum uptake settings per activity. | F108: Not Started
B109: 89 | C109: Activity Management | D109: Activity Scheduling & Integration | E109: Schedule activities with optional timetable periods. Effortlessly copy activities from previous terms. Integrated with assessment module and report cards. Export wizard for activity group access. | F109: Not Started
B110: ▶ ASSESSMENT PREMIUM
B111: 90 | C111: Assessment Premium | D111: Gradebook & Mark Entry | E111: Record marks in gradebooks with colour-coded percentage boundaries. Add notes to individual marks. Google Classroom one-way sync to pull marks into Ed-Admin. Bulk download mark sheets to Excel. | F111: Completed
B112: 91 | C112: Assessment Premium | D112: Feedback & Effort Ratings | E112: Provide qualitative comments per task uploaded to marks live feed. Provide instant effort ratings per task feeding into the markbook. Summative effort ratings appear on reports. | F112: Completed
B113: 92 | C113: Assessment Premium | D113: Results Analysis | E113: View top performing students by ranking. Export full mark schedules, summary fields (effort, behaviour, work ethic), and assessment criteria. In-depth portfolio analysis by subject or phase. Custom field selection including gender, attendance, house, and more. | F113: Completed
B114: 93 | C114: Assessment Premium | D114: Report Card Publishing | E114: Central control point to publish report cards by grade and template. Set permissions for targeted staff. Bulk report card checking, downloading, and archiving after publishing. | F114: Completed
...

Sheet SLA Ed admin Feature List
B1: ED-ADMIN — COMPLETE FEATURE LIST
B5: Total Features: 151 | Function Areas: 30 | Source: Ed-Admin Complete Feature List
B7: # | C7: FUNCTION AREA | D7: FEATURE NAME | E7: DESCRIPTION | F7: Implementation Status
B8: ▶ ADMISSIONS
B9: 1 | C9: Admissions | D9: Online Application — Website Integration | E9: Enrolment application form integrated into the school website and Ed-Admin, capturing data and delivering it directly to the Admissions Module. | F9: In Progress
B10: 2 | C10: Admissions | D10: Online Application — Automatic Email Alerts | E10: Automatic email alerts sent to the Admissions Registrar when new applications are submitted online. | F10: In Progress
B11: 3 | C11: Admissions | D11: Online Application — Status Update Notifications | E11: Automatic email alerts sent to parents and admissions staff for all status updates throughout the application process. | F11: In Progress
B12: 8 | C12: Admissions | D12: Online Application — Document Uploads | E12: Parents can upload supporting documents including school reports, birth certificates, and IDs. Student photo upload also supported. | F12: Not Started
B13: 9 | C13: Admissions | D13: Online Application — Field Configuration | E13: Full control over which fields are optional, mandatory, or disabled. Public-facing labels can be renamed up to 100 characters. | F13: Completed
B14: 10 | C14: Admissions | D14: Online Application — Branding | E14: Institution colours can be applied for branding. A full copy of the completed application is emailed to the primary guardian. | F14: Not Started
B15: 11 | C15: Admissions | D15: Admission Tracking — Data Management | E15: Parents capture application data into the core system; staff can add additional information or make changes. | F15: In Progress
B16: 12 | C16: Admissions | D16: Admission Tracking — Online Payments | E16: Payment for registration can be set up to process new applications online. | F16: Not Started
B17: 14 | C17: Admissions | D17: Admission Tracking — Configurable Status Steps | E17: Ability to configure the admission process with any number of steps and statuses (e.g. Waiting, Assessed, Offered Position). Additional custom statuses can be added. | F17: Completed
B18: 15 | C18: Admissions | D18: Admission Tracking — Progress Tracking | E18: Micro-manage the admission process by breaking each status into smaller steps; take notes, upload attachments and mark each step complete. | F18: Completed
B19: 16 | C19: Admissions | D19: Admission Tracking — Weighted Matrix | E19: Ability to weight applications using a matrix with criteria such as living within a radius, parents are alumni, reference from previous institution, etc. | F19: Not Started
B20: 17 | C20: Admissions | D20: Admission Tracking — Bulk Communication | E20: Bulk email and SMS to applicant groups based on status, year applied for, etc. Content personalised using merge codes. | F20: Not Started
... B26: 23 | C26: Admissions | D26: Admission Reports | E26: Reports listing applications by grade, year of entry, or waiting list position. Configurable analysis reports for current year, upcoming year, and up to ten years into the future. | F26: Not Started
B27: ▶ DASHBOARD
B28: 43 | C28: Dashboard | D28: Information Hub | E28: Dynamic information portal with instant notice board for forums, news, events, and push notifications to Mobile Apps. | F28: Completed
B29: 44 | C29: Dashboard | D29: Budget Dashboard | E29: Users can view their transactions, data, and charts against budget codes directly on the dashboard. | F29: In Progress
B30: 45 | C30: Dashboard | D30: Data Snapshots | E30: Graphical data snapshots showing basic statistics about the school and students. | F30: Completed
B31: 46 | C31: Dashboard | D31: Security & Customisation | E31: Security levels restrict staff to data relevant to their department. Users can customise their own dashboard view. Ability to post media (pictures, videos) and add hyperlinks to news. | F31: Completed
B32: ▶ ENQUIRY
B33: 47 | C33: Enquiry | D33: Online Enquiry Form | E33: Complement your website with online enquiry forms for potential parents and students. Track and respond to all enquiries with status updates. | F33: In Progress
B34: 48 | C34: Enquiry | D34: Automatic Emails & Communication Log | E34: Enquiries automatically emailed to single or multiple addresses. View all communications with a party including dates, times, and staff member details. Assign follow-up actions. | F34: In Progress
B35: ▶ PORTALS & MOBILE APPS
B36: 49 | C36: Portals & Mobile Apps | D36: Parent Portal — Comprehensive Access | E36: Parents monitor student progress remotely: attendance, report cards, calendar, timetable, merits/demerits, activities, library, finance statements, health records, and more. One login for all children. | F36: Completed
B37: 51 | C37: Portals & Mobile Apps | D37: Customisable Portal Features | E37: Institutions control which features are shown or hidden: News, Calendar, Assessment Feed, LBM, Activities, Report Cards, Attendance, Communication, Library, Re-enrolment, Parent-Teacher Meetings, Finance, Health Records, Documents, and more. | F37: Completed
B38: 52 | C38: Portals & Mobile Apps | D38: Parent-Teacher Communication | E38: Direct email and messaging between parents, students, teachers, and staff from within the portal. Integrated email and chat functionality. | F38: In Progress
B39: 53 | C39: Portals & Mobile Apps | D39: Online Information Updates | E39: Parents and students update personal information, medical history, and contact details online; changes can be held pending institutional approval. | F39: Completed | G39: Sessions with parents to onboard them on the system required
B40: 54 | C40: Portals & Mobile Apps | D40: Finance on Portal | E40: View statements and outstanding balances, obtain and pay invoices, view fee account balances, and print past and present invoices via the portal. | F40: Not Started
B41: ▶ PARENT RECORDS
B42: 59 | C42: Parent Records | D42: Comprehensive Sponsor Database | E42: Easy view of both guardians and sponsors on one screen. Option for additional guardians (Guardian 3 and 4). Contact, address, and emergency details all in one place. | F42: Completed
B43: 60 | C43: Parent Records | D43: Communication & Audit Log | E43: Communication log of all correspondence. Full audit history logging every action including portal login history. Password security compliant with POPI Act. | F43: Not Started
B44: 61 | C44: Parent Records | D44: Reports & Analysis | E44: Parent analysis reports to identify missing records (emails, phone numbers, addresses). Sibling reports to see all related students. | F44: In Progress
B45: 62 | C45: Parent Records | D45: Direct Email & SMS | E45: Send email or SMS directly to a parent with a click of a button from within the Parent Records module. | F45: Completed
B46: ▶ STUDENT RECORDS
B47: 63 | C47: Student Records | D47: Centralised Student Database | E47: Full registration information including start date, previous institution, and transfer details. Linked to parent records to avoid duplication. Powerful search by name, grade, class, or status. | F47: Completed
B48: 64 | C48: Student Records | D48: Academic & Attendance View | E48: View academic progress, extracurricular activities, attendance records, timetables, and fee schedules directly from within the Student module. | F48: Completed
B49: 66 | C49: Student Records | D49: Communication Log | E49: Communication log showing all correspondence from the institution to the student. Direct email and SMS from student records. | F49: Completed
B50: 67 | C50: Student Records | D50: Behaviour & Learning Support | E50: Quick view of LBM (merit/demerit) records. View learning support records including therapy, assessments, and exam accommodations. | F50: Completed
B51: 68 | C51: Student Records | D51: Full Audit History | E51: Complete audit trail logging every change with user, computer, and event details. Portal login history tracked. | F51: Completed
B52: 69 | C52: Student Records | D52: Reporting & Analysis | E52: Dynamic report writer. Class lists with photos and custom columns. Enrolment analysis, student data analysis (missing data, siblings, parent links), statistical reports by gender, nationality, religion, and class. | F52: Completed
B53: 70 | C53: Student Records | D53: Transfer & Custom Fields | E53: Access transfer cards and custom designs. National number capture (Lurits/Cemis). Student house reports. Student leaving/starting report by date range. | F53: Completed
B54: ▶ PASTORAL CARE
B55: ▶ LEAVE MANAGEMENT
B56: 75 | C56: Leave Management | D56: Online Leave Application | E56: All staff apply for leave online selecting from a range of leave types and attaching supporting documents. Email notifications to applicant and approval staff. Automated approval notifications. | F56: Completed
B57: 76 | C57: Leave Management | D57: Leave Approval Process | E57: Approval uses the Reporting To hierarchy from the HR module. Configurable approval tiers (1, 2, or 3 levels). Leave administrator can override approvals. Applications rejected with notes kept on record. | F57: In Progress
B58: 77 | C58: Leave Management | D58: Paperless Leave Solution | E58: All leave application, documents and approvals are fully online. Leave administrators can stay in the loop, retract approved leaves, or intercept the approval process. | F58: Completed
B59: ▶ STAFF ATTENDANCE
B60: 79 | C60: Staff Attendance | D60: Work Schedules | E60: Group staff into work schedule groups covering full-time, part-time and weekend staff. Exclude non-working days, public holidays, and term breaks. SMS and email notifications for late arrivals or early departures. | F60: Completed
B61: 80 | C61: Staff Attendance | D61: Reports & Communications | E61: Staff attendance reports across the whole institution or by specific campus. All communications personalised using merge codes. Configurable email templates for the Leave Administrator. | F61: In Progress
B62: ▶ ACADEMIC MANAGEMENT
B63: 81 | C63: Academic Management | D63: Subject & Class Management | E63: Manage full subject range, assign rooms to teachers, allocate teachers to subjects, enrol students in classes. Create sets and divisions within subjects. Copy and re-integrate timetables term to term. | F63: Completed
B64: 82 | C64: Academic Management | D64: Timetable Features | E64: Flexible period allocations (single, double, triple). Auto-detect conflict resolution. Import timetables from Excel, ASC, or Timetabler. Subject colour allocations. Multi-level student allocations across grades. | F64: Completed
B65: 83 | C65: Academic Management | D65: Assessment & Gradebooks | E65: Create custom gradebooks with flexible weightings. Bulk generate average and promotion marks. Set Year Mark weightings. SASAMS gradebook import for CAP schools. | F65: Completed
B66: 84 | C66: Academic Management | D66: Grade Schedules & Assessment Criteria | E66: Create schedules per grade matching percentages to letters or numbers (A*, A, B, C or 7, 6, 5, 4). Create assessment criteria linked to option sets (letters, numbers, symbols). | F66: Completed
B67: 85 | C67: Academic Management | D67: Report Cards | E67: Control subjects, comments, page sequence, images, and dates on report cards. Use comment banks. Bulk print by grade or class. Publish report cards to Mobile Apps with access control. | F67: Completed
B68: 86 | C68: Academic Management | D68: Academic Reports | E68: Range of standard and customisable analysis reports. Mark analysis, registers, class lists, reviews, and transcript generation. Export to PDF or print. Auto-populate term reports once assessments entered. | F68: In Progress
B69: ▶ ACTIVITY MANAGEMENT
B70: 87 | C70: Activity Management | D70: Cultural & Sports Groups | E70: Add/remove students and teachers from clubs, societies, music, and sports. Record co-curricular and sport involvement on student profiles. Take attendance via web and mobile app. | F70: Completed
B71: 88 | C71: Activity Management | D71: Activity Categories & Classifications | E71: Create unlimited activity groups and sub-categories (music, extra-curricular, sports). Classify activities by age or grade (e.g. U12, U14, open). Minimum and maximum uptake settings per activity. | F71: Completed
B72: 89 | C72: Activity Management | D72: Activity Scheduling & Integration | E72: Schedule activities with optional timetable periods. Effortlessly copy activities from previous terms. Integrated with assessment module and report cards. Export wizard for activity group access. | F72: Completed
B73: ▶ ASSESSMENT PREMIUM
B74: 90 | C74: Assessment Premium | D74: Gradebook & Mark Entry | E74: Record marks in gradebooks with colour-coded percentage boundaries. Add notes to individual marks. Google Classroom one-way sync to pull marks into Ed-Admin. Bulk download mark sheets to Excel. | F74: Completed
B75: 91 | C75: Assessment Premium | D75: Feedback & Effort Ratings | E75: Provide qualitative comments per task uploaded to marks live feed. Provide instant effort ratings per task feeding into the markbook. Summative effort ratings appear on reports. | F75: Completed
B76: 92 | C76: Assessment Premium | D76: Results Analysis | E76: View top performing students by ranking. Export full mark schedules, summary fields (effort, behaviour, work ethic), and assessment criteria. In-depth portfolio analysis by subject or phase. Custom field selection including gender, attendance, house, and more. | F76: Completed
B77: 93 | C77: Assessment Premium | D77: Report Card Publishing | E77: Central control point to publish report cards by grade and template. Set permissions for targeted staff. Bulk report card checking, downloading, and archiving after publishing. | F77: Completed
B78: 94 | C78: Assessment Premium | D78: Insight Menu | E78: Real-time access to critical student data: attendance, birthdays, comments, health data, leaving dates, learning support, parent-teacher notes, health incidents, and LBM records. | F78: Completed
B79: ▶ ATTENDANCE
B80: 95 | C80: Attendance | D80: Daily & Periodic Attendance | E80: Easy attendance recording on web and mobile. Multiple attendance types. Timetable integration including ASC for periodic attendance. House, Sick Bay, Cultural, Activities, and Sport attendance all supported. | F80: Completed
B81: 96 | C81: Attendance | D81: Attendance History & Reporting | E81: Full attendance history by year for groups, tutor groups, and houses. Exception report for staff who have not taken attendance. Periodic attendance export. Compare attendance statistics across academic years and classes. | F81: Completed
B82: 97 | C82: Attendance | D82: Parent Notifications | E82: Generate automatic notification letters/emails when students are absent. Identify unwelcome absence trends. Biometric fingerprint integration at school entrance or classroom. | F82: Completed
B83: 98 | C83: Attendance | D83: Gradebook Integration | E83: Integrate attendance summaries into end-of-term reporting depending on the institution's reporting format. | F83: Completed
B84: ▶ CURRICULUM MANAGEMENT & LMS
B85: ▶ LEARNING & BEHAVIOUR (LBM)
B86: 103 | C86: Learning & Behaviour (LBM) | D86: Merit & Demerit System | E86: Easy issuing of demerits and merits via desktop or mobile app. Integrated academic and pastoral discipline system feeding appropriate workflows. Full history accessible to teachers. | F86: Completed
B87: 104 | C87: Learning & Behaviour (LBM) | D87: Behaviour & Consequence Records | E87: Document disciplinary incidents in detail. Track improper conduct, consequences, detentions, and rewards. Setup rules for automatic calculation of consequences and rewards. Track penalties served or owed. | F87: In Progress
B88: 105 | C88: Learning & Behaviour (LBM) | D88: Parent & Student Access | E88: Parents and students optionally access behaviour profiles privately and securely online via the Parent and Student App. | F88: In Progress
B89: 106 | C89: Learning & Behaviour (LBM) | D89: Reports & Notifications | E89: Customisable report writer for statistical reports, letters, and documents. Automatic email and SMS notifications for detentions. Discipline data filtered by pupil, type, term, or grade. Code of conduct report cards and reward certificates. | F89: Completed
B90: ▶ SERVER & INFRASTRUCTURE
B91: 113 | C91: Server & Infrastructure | D91: Performance & Availability | E91: Real-time updates with no lag. Available 24 hours a day. Remote access for dedicated servers. Overnight maintenance updates managed by the provider — no IT department involvement needed. | F91: Not Started
B92: 114 | C92: Server & Infrastructure | D92: Security | E92: Single Sign On (SSO). Two-Factor Authentication. Granular user role allocation. Encrypted password storage. POPIA compliant. Transactional log of all changes. | F92: Not Started
B93: 115 | C93: Server & Infrastructure | D93: Recovery & Support | E93: Nightly backups with less than 24-hour recovery. 24/7 support. Access to all client upgrades. | F93: Not Started
B94: 116 | C94: Server & Infrastructure | D94: Interoperability | E94: Cross-browser compatible. Android and iOS apps. Integration with Microsoft Office Suite and Microsoft Teams API. Modern, intuitive user interface with table filtering and column customisation. | F94: Not Started
B95: ▶ CONTACTS
B96: 120 | C96: Contacts | D96: Contact Database | E96: Record and access suppliers, customers, and general contacts. Bulk email and SMS to groups or individuals. Bind multiple persons to a contact. Categorise as General, Supplier, or Customer. Attach documentation. View suppliers in multi-currency. | F96: Completed
B97: ▶ FEE ADMINISTRATION
B98: 121 | C98: Fee Administration | D98: Student Fee Billing | E98: Automatic billing of fees monthly, termly, or yearly. Automated bursaries, scholarships, and discounts. Billing for aftercare, activities, outings, and excursions. Staff discounted fee provisions. Multi-year billing for pre-enrolled students. | F98: In Progress
B99: 122 | C99: Fee Administration | D99: Payment Plans & Reminders | E99: Each debtor can have one or more commitment plans. Automated email and SMS payment reminders before due dates. Schedule personal call reminders for debtor staff. | F99: In Progress
B100: 123 | C100: Fee Administration | D100: Batch Invoicing | E100: Batch invoicing for ad-hoc activities (outings, music lessons, aftercare). Direct import of student data from billable activities. Mass import of historical debtor transactions. | F100: In Progress
B101: 124 | C101: Fee Administration | D101: Point of Sale — Uniforms & Books | E101: Invoice for stocked items (uniforms, textbooks) and generate receipts on the spot. Integration with inventory database. Receipt can be printed, emailed, or SMSed. Stock automatically updated in real time with full audit trail. | F101: In Progress
B102: 125 | C102: Fee Administration | D102: Debit Order Processing | E102: Process monthly, quarterly, or 6-monthly debit orders. Multiple debit orders per debtor. Setup for outstanding or fixed amounts. Automatic EFT file generation for bank upload. Import debit order details from prior systems. | F102: In Progress
B103: 126 | C103: Fee Administration | D103: Aged Balance Management | E103: View aged balances by debtor type (boarders, monthly payers, debit order, termly, scholarships, 60/90 days overdue). Export to Excel. Generate for any period including prior years. | F103: In Progress
B104: 127 | C104: Fee Administration | D104: Debtor Grouping & CRM | E104: Group debtors into risk categories (Red Accounts, Handed-over, Past Debtors). View payment patterns. Email and SMS debtors directly from CRM with full communication log history. | F104: In Progress
B105: 128 | C105: Fee Administration | D105: Receipting Functions | E105: Quick 15-second receipt processing. Allocate receipts to oldest invoices or specific invoices. Auto-email receipts to debtors. Batch receipting via bank statement import (XLSX and CSV). Auto-reverse receipts for corrections. Multiple currency support. | F105: In Progress
B106: 129 | C106: Fee Administration | D106: Statements | E106: Consolidated or per-student statement formats. Configure components shown on statements. Address statements to family, specific guardian, or external company. Bulk email statements. Single or batch printing. | F106: In Progress
B107: 130 | C107: Fee Administration | D107: Refundable Deposits & Debentures | E107: Manage any number of ledger types (debtor or creditor) per parent or student. Transfer funds between ledgers. Show or hide non-tuition fee transactions on statements. | F107: In Progress
B108: ▶ GENERAL LEDGER & BUDGETING
B109: 131 | C109: General Ledger & Budgeting | D109: Chart of Accounts | E109: Flexible chart of accounts supporting 6–12 digit ranges. Structured for multiple campuses (up to 100,000). Supports income, expense, and other standard groupings with full migration capability from other systems. | F109: Completed
...

Sheet Ed admin Summary
A1: Silverleaf BPR — Ed-Admin Implementation Dashboard
A2: Tech & Automation Project, Q2 2026. Pulled automatically from the Feature Detail tab.
A4: Total Features | B4: Completed | C4: Completed & Used | D4: In Progress | E4: Not Started | F4: Will not be Used
A5: 151 | B5: 41 | C5: 22 | D5: 24 | E5: 47 | F5: 10
A8: Total Ed admin Modules | B8: Total Features | C8: 100% Features for SLA | D8: Completed | E8: In Progress | F8: Not Started | G8: % Complete
A9: Admissions | B9: =COUNTIF('Ed admin Full Feature List'!$C$9:$C$190,$A9) -> 23 | C9: =COUNTIF('SLA Ed admin Feature List'!$C$9:$C$160,$A9) -> 18 | D9: =COUNTIFS('SLA Ed admin Feature List'!$C$9:$C$160,$A9,'SLA Ed admin Feature List'!$F$9:$F$160,"Completed") -> 7 | E9: =COUNTIFS('SLA Ed admin Feature List'!$C$9:$C$160,$A9,'SLA Ed admin Feature List'!$F$9:$F$160,"In progress") -> 4 | F9: =COUNTIFS('SLA Ed admin Feature List'!$C$9:$C$160,$A9,'SLA Ed admin Feature List'!$F$9:$F$160,"Not started") -> 7 | G9: =D9/C9 -> 0.38888889
A10: Dashboard | B10: =COUNTIF('Ed admin Full Feature List'!$C$9:$C$190,$A10) -> 4 | C10: =COUNTIF('SLA Ed admin Feature List'!$C$9:$C$160,$A10) -> 4 | D10: =COUNTIFS('SLA Ed admin Feature List'!$C$9:$C$160,$A10,'SLA Ed admin Feature List'!$F$9:$F$160,"Completed") -> 3 | E10: =COUNTIFS('SLA Ed admin Feature List'!$C$9:$C$160,$A10,'SLA Ed admin Feature List'!$F$9:$F$160,"In progress") -> 1 | F10: =COUNTIFS('SLA Ed admin Feature List'!$C$9:$C$160,$A10,'SLA Ed admin Feature List'!$F$9:$F$160,"Not started") -> 0 | G10: =D10/C10 -> 0.75
A11: Enquiry | B11: =COUNTIF('Ed admin Full Feature List'!$C$9:$C$190,$A11) -> 2 | C11: =COUNTIF('SLA Ed admin Feature List'!$C$9:$C$160,$A11) -> 2 | D11: =COUNTIFS('SLA Ed admin Feature List'!$C$9:$C$160,$A11,'SLA Ed admin Feature List'!$F$9:$F$160,"Completed") -> 0 | E11: =COUNTIFS('SLA Ed admin Feature List'!$C$9:$C$160,$A11,'SLA Ed admin Feature List'!$F$9:$F$160,"In progress") -> 2 | F11: =COUNTIFS('SLA Ed admin Feature List'!$C$9:$C$160,$A11,'SLA Ed admin Feature List'!$F$9:$F$160,"Not started") -> 0 | G11: =D11/C11 -> 0
A12: Portals & Mobile Apps | B12: =COUNTIF('Ed admin Full Feature List'!$C$9:$C$190,$A12) -> 10 | C12: =COUNTIF('SLA Ed admin Feature List'!$C$9:$C$160,$A12) -> 5 | D12: =COUNTIFS('SLA Ed admin Feature List'!$C$9:$C$160,$A12,'SLA Ed admin Feature List'!$F$9:$F$160,"Completed") -> 3 | E12: =COUNTIFS('SLA Ed admin Feature List'!$C$9:$C$160,$A12,'SLA Ed admin Feature List'!$F$9:$F$160,"In progress") -> 1 | F12: =COUNTIFS('SLA Ed admin Feature List'!$C$9:$C$160,$A12,'SLA Ed admin Feature List'!$F$9:$F$160,"Not started") -> 1 | G12: =D12/C12 -> 0.6
A13: Parent Records | B13: =COUNTIF('Ed admin Full Feature List'!$C$9:$C$190,$A13) -> 4 | C13: =COUNTIF('SLA Ed admin Feature List'!$C$9:$C$160,$A13) -> 4 | D13: =COUNTIFS('SLA Ed admin Feature List'!$C$9:$C$160,$A13,'SLA Ed admin Feature List'!$F$9:$F$160,"Completed") -> 2 | E13: =COUNTIFS('SLA Ed admin Feature List'!$C$9:$C$160,$A13,'SLA Ed admin Feature List'!$F$9:$F$160,"In progress") -> 1 | F13: =COUNTIFS('SLA Ed admin Feature List'!$C$9:$C$160,$A13,'SLA Ed admin Feature List'!$F$9:$F$160,"Not started") -> 1 | G13: =D13/C13 -> 0.5
A14: Student Records | B14: =COUNTIF('Ed admin Full Feature List'!$C$9:$C$190,$A14) -> 8 | C14: =COUNTIF('SLA Ed admin Feature List'!$C$9:$C$160,$A14) -> 7 | D14: =COUNTIFS('SLA Ed admin Feature List'!$C$9:$C$160,$A14,'SLA Ed admin Feature List'!$F$9:$F$160,"Completed") -> 7 | E14: =COUNTIFS('SLA Ed admin Feature List'!$C$9:$C$160,$A14,'SLA Ed admin Feature List'!$F$9:$F$160,"In progress") -> 0 | F14: =COUNTIFS('SLA Ed admin Feature List'!$C$9:$C$160,$A14,'SLA Ed admin Feature List'!$F$9:$F$160,"Not started") -> 0 | G14: =D14/C14 -> 1
A15: Leave Management | B15: =COUNTIF('Ed admin Full Feature List'!$C$9:$C$190,$A15) -> 3 | C15: =COUNTIF('SLA Ed admin Feature List'!$C$9:$C$160,$A15) -> 3 | D15: =COUNTIFS('SLA Ed admin Feature List'!$C$9:$C$160,$A15,'SLA Ed admin Feature List'!$F$9:$F$160,"Completed") -> 2 | E15: =COUNTIFS('SLA Ed admin Feature List'!$C$9:$C$160,$A15,'SLA Ed admin Feature List'!$F$9:$F$160,"In progress") -> 1 | F15: =COUNTIFS('SLA Ed admin Feature List'!$C$9:$C$160,$A15,'SLA Ed admin Feature List'!$F$9:$F$160,"Not started") -> 0 | G15: =D15/C15 -> 0.66666667
A16: Staff Attendance | B16: =COUNTIF('Ed admin Full Feature List'!$C$9:$C$190,$A16) -> 3 | C16: =COUNTIF('SLA Ed admin Feature List'!$C$9:$C$160,$A16) -> 2 | D16: =COUNTIFS('SLA Ed admin Feature List'!$C$9:$C$160,$A16,'SLA Ed admin Feature List'!$F$9:$F$160,"Completed") -> 1 | E16: =COUNTIFS('SLA Ed admin Feature List'!$C$9:$C$160,$A16,'SLA Ed admin Feature List'!$F$9:$F$160,"In progress") -> 1 | F16: =COUNTIFS('SLA Ed admin Feature List'!$C$9:$C$160,$A16,'SLA Ed admin Feature List'!$F$9:$F$160,"Not started") -> 0 | G16: =D16/C16 -> 0.5
A17: Academic Management | B17: =COUNTIF('Ed admin Full Feature List'!$C$9:$C$190,$A17) -> 6 | C17: =COUNTIF('SLA Ed admin Feature List'!$C$9:$C$160,$A17) -> 6 | D17: =COUNTIFS('SLA Ed admin Feature List'!$C$9:$C$160,$A17,'SLA Ed admin Feature List'!$F$9:$F$160,"Completed") -> 5 | E17: =COUNTIFS('SLA Ed admin Feature List'!$C$9:$C$160,$A17,'SLA Ed admin Feature List'!$F$9:$F$160,"In progress") -> 1 | F17: =COUNTIFS('SLA Ed admin Feature List'!$C$9:$C$160,$A17,'SLA Ed admin Feature List'!$F$9:$F$160,"Not started") -> 0 | G17: =D17/C17 -> 0.83333333
A18: Activity Management | B18: =COUNTIF('Ed admin Full Feature List'!$C$9:$C$190,$A18) -> 3 | C18: =COUNTIF('SLA Ed admin Feature List'!$C$9:$C$160,$A18) -> 3 | D18: =COUNTIFS('SLA Ed admin Feature List'!$C$9:$C$160,$A18,'SLA Ed admin Feature List'!$F$9:$F$160,"Completed") -> 3 | E18: =COUNTIFS('SLA Ed admin Feature List'!$C$9:$C$160,$A18,'SLA Ed admin Feature List'!$F$9:$F$160,"In progress") -> 0 | F18: =COUNTIFS('SLA Ed admin Feature List'!$C$9:$C$160,$A18,'SLA Ed admin Feature List'!$F$9:$F$160,"Not started") -> 0 | G18: =D18/C18 -> 1
A19: Assessment Premium | B19: =COUNTIF('Ed admin Full Feature List'!$C$9:$C$190,$A19) -> 5 | C19: =COUNTIF('SLA Ed admin Feature List'!$C$9:$C$160,$A19) -> 5 | D19: =COUNTIFS('SLA Ed admin Feature List'!$C$9:$C$160,$A19,'SLA Ed admin Feature List'!$F$9:$F$160,"Completed") -> 5 | E19: =COUNTIFS('SLA Ed admin Feature List'!$C$9:$C$160,$A19,'SLA Ed admin Feature List'!$F$9:$F$160,"In progress") -> 0 | F19: =COUNTIFS('SLA Ed admin Feature List'!$C$9:$C$160,$A19,'SLA Ed admin Feature List'!$F$9:$F$160,"Not started") -> 0 | G19: =D19/C19 -> 1
A20: Attendance | B20: =COUNTIF('Ed admin Full Feature List'!$C$9:$C$190,$A20) -> 4 | C20: =COUNTIF('SLA Ed admin Feature List'!$C$9:$C$160,$A20) -> 4 | D20: =COUNTIFS('SLA Ed admin Feature List'!$C$9:$C$160,$A20,'SLA Ed admin Feature List'!$F$9:$F$160,"Completed") -> 4 | E20: =COUNTIFS('SLA Ed admin Feature List'!$C$9:$C$160,$A20,'SLA Ed admin Feature List'!$F$9:$F$160,"In progress") -> 0 | F20: =COUNTIFS('SLA Ed admin Feature List'!$C$9:$C$160,$A20,'SLA Ed admin Feature List'!$F$9:$F$160,"Not started") -> 0 | G20: =D20/C20 -> 1
... A27: Requisitions & Purchasing | B27: =COUNTIF('Ed admin Full Feature List'!$C$9:$C$190,$A27) -> 2 | C27: =COUNTIF('SLA Ed admin Feature List'!$C$9:$C$160,$A27) -> 2 | D27: =COUNTIFS('SLA Ed admin Feature List'!$C$9:$C$160,$A27,'SLA Ed admin Feature List'!$F$9:$F$160,"Completed") -> 0 | E27: =COUNTIFS('SLA Ed admin Feature List'!$C$9:$C$160,$A27,'SLA Ed admin Feature List'!$F$9:$F$160,"In progress") -> 0 | F27: =COUNTIFS('SLA Ed admin Feature List'!$C$9:$C$160,$A27,'SLA Ed admin Feature List'!$F$9:$F$160,"Not started") -> 0 | G27: =D27/C27 -> 0
A28: TOTAL | B28: =sum(B9:B27) -> 105 | C28: =sum(C9:C27) -> 93 | D28: =sum(D9:D27) -> 49 | E28: =sum(E9:E27) -> 29 | F28: =sum(F9:F27) -> 13 | G28: =D28/C28 -> 0.52688172
A30: Status | B30: Count
A31: Completed | B31: =countif('SLA Ed admin Feature List'!F:F,"Completed") -> 49
A32: In Progress | B32: =countif('SLA Ed admin Feature List'!F:F,"In progress") -> 29
A33: Not Started | B33: =countif('SLA Ed admin Feature List'!F:F,"Not started") -> 13

Sheet SLA Digital Systems
B1: Digital Tools & Systems Register
B2: A complete inventory of all technology platforms and digital systems in active use across the SLA network — including their purpose, responsible lead, and the departments they serve.
A3: Sn | B3: System | C3: Category | D3: Purpose / Usage | E3: Lead Person | F3: Departments
A4: 1 | B4: Slack | C4: Communication | D4: A team messaging and collaboration platform used for real-time internal communication, departmental channels, file sharing, and project discussions across the SLA network. | E4: Paul | F4: OPS, Marketing, Finance, TA, SLT
A5: 2 | B5: WhatsApp | C5: Communication | D5: A mobile messaging application used for fast, day-to-day informal communication and quick updates among all staff members across all campuses. | E5: Lisa | F5: All
A6: 3 | B6: Email | C6: Communication | D6: The primary formal communication channel used for all official organizational correspondence, announcements, external partner communication, and document sharing. | E6: Paul | F6: All
A7: 4 | B7: Google Workspace | C7: Productivity | D7: A cloud-based productivity and collaboration suite that provides staff with access to Gmail, Google Drive (file storage), Google Docs, Sheets, Slides, and Meet — enabling real-time teamwork and document management. | E7: Paul | F7: Marketing, OPS, Finance
A8: 5 | B8: QuickBooks | C8: Finance | D8: An accounting and financial management software used to record income and expenses, manage invoices, track cash flow, and generate financial reports for the Finance team and leadership. | E8: Mercy | F8: Finance
A9: 6 | B9: PayTan | C9: HR/Finance | D9: An integrated HR and payments platform used to process staff leave requests, manage payroll, and handle school fee payments submitted by parents and guardians. | E9: Mercy | F9: HR, Finance
A10: 7 | B10: Ed-admin | C10: School Info System | D10: A comprehensive school management system used to maintain student records, manage the admissions process, track academic data, and streamline administrative workflows across all campuses. | E10: Paul | F10: All
A11: 8 | B11: RunShule | C11: School Info System | D11: A school operations platform used for tracking daily student attendance, managing fee collection and payment records, and facilitating direct communication between the school and parents. | E11: Mercy | F11: Finance
A12: 9 | B12: Google Maps/Earth | C12: Logistics | D12: A geolocation and mapping tool used by the Operations team to plan and optimize student transport routes, visualize campus locations, and support field logistics and planning. | E12: Baraka | F12: OPS
A13: 13 | B13: Canva for Education | C13: Design | D13: A graphic design platform used to create professional visual content including marketing materials, social media graphics, school presentations, certificates, newsletters, and educational resources. | E13: Erick | F13: Marketing, Consultants
A14: 13 | B14: Wix | C14: Web Management | D14: A website creation and content management platform used to build, update, and maintain the SLA public-facing website, including admissions pages, campus information, and announcements. | E14: Paul / Nehemia | F14: Marketing
A15: 13 | B15: ChatGPT Business | C15: AI Productivity | D15: An AI-powered writing and research assistant used across departments for drafting content, conducting research, summarizing documents, and exploring workflow automation possibilities. | E15: Paul / Krupa | F15: All
... A19: 16 | B19: Classdojo | C19: Education Technology | D19: communication and behavior management platform designed to connect teachers, students, and families to build positive classroom communities | E19: Talent Manager | F19: Academic

Sheet LIVE Systems
A1: Department
A2: Expansion | B2: Expansion System
A3: HR | B3: Onboarding System
A4: HR | B4: Hiring
A5: ops | B5: transport
A6: ops | B6: ticketing system
A7: mark/student exp | B7: marketing/student experience
A8: alloyce | B8: Talent ACADEMY
A9: julius | B9: lesson plans

Sheet Department Implementation
A1: Department | B1: # | C1: FUNCTION AREA | D1: FEATURE NAME | E1: DESCRIPTION | F1: Implementation Status
C2: Marketing Department
C3: Admissions | D3: Online Application — Form creation | E3: Online aplication form is set up in the backend and ready availbale to use by the admissions and marketing team | F3: Completed
C4: Admissions | D4: Online Application — (Admissions team training) | E4: Admissions team and marketig team trained on how to access and use the online form | F4: In Progress
C5: Admissions
C6: Admissions | D6: Online Application — Website Integration | E6: Enrolment application form integrated into the school website and Ed-Admin, capturing data and delivering it directly to the Admissions Module. | F6: Not Started
C10: Finance Department
C14: Student experience Department
